{"skeleton":{"hash":"JL2hWrS8YtiQsS8sYduDjAOhy1E","spine":"3.7.94","width":700,"height":162,"images":"./images/","audio":"E:/congty/spine/shan/xoc dia/start game"},"bones":[{"name":"root"},{"name":"bone","parent":"root","x":1.19,"y":-99.77},{"name":"start game copy","parent":"bone","length":43.97,"rotation":87.84,"x":4.15,"y":128.49},{"name":"ribbon","parent":"bone","length":92.86,"rotation":1.02,"x":8.29,"y":124.35}],"slots":[{"name":"ribbon","bone":"ribbon","attachment":"ribbon"},{"name":"start game copy","bone":"start game copy","attachment":"start game copy"}],"skins":{"default":{"ribbon":{"ribbon":{"x":-9.91,"y":-23.81,"rotation":-1.02,"width":700,"height":162}},"start game copy":{"start game copy":{"x":-1.78,"y":3.83,"rotation":-87.84,"width":347,"height":63}}}},"animations":{"animation":{"slots":{"ribbon":{"color":[{"time":0,"color":"ffffff00"},{"time":0.0667,"color":"ffffffff"}]},"start game copy":{"color":[{"time":0.1667,"color":"ffffff00"},{"time":0.2667,"color":"ffffffff"}],"attachment":[{"time":0,"name":null},{"time":0.1667,"name":"start game copy"}]}},"bones":{"ribbon":{"rotate":[{"time":0,"angle":0,"curve":"stepped"},{"time":0.1667,"angle":0,"curve":"stepped"},{"time":0.2667,"angle":0,"curve":"stepped"},{"time":0.3333,"angle":0,"curve":"stepped"},{"time":0.8667,"angle":0,"curve":"stepped"},{"time":1.3333,"angle":0}],"translate":[{"time":0,"x":0,"y":0,"curve":"stepped"},{"time":0.1667,"x":0,"y":0,"curve":"stepped"},{"time":0.2667,"x":0,"y":0,"curve":"stepped"},{"time":0.3333,"x":0,"y":0,"curve":"stepped"},{"time":0.8667,"x":0,"y":0,"curve":"stepped"},{"time":1.3333,"x":0,"y":0}],"scale":[{"time":0,"x":1.565,"y":1.565},{"time":0.1667,"x":1,"y":1},{"time":0.2667,"x":1.219,"y":1.219},{"time":0.3333,"x":1,"y":1,"curve":"stepped"},{"time":0.8667,"x":1,"y":1,"curve":"stepped"},{"time":1.3333,"x":1,"y":1}],"shear":[{"time":0,"x":0,"y":0,"curve":"stepped"},{"time":0.1667,"x":0,"y":0,"curve":"stepped"},{"time":0.2667,"x":0,"y":0,"curve":"stepped"},{"time":0.3333,"x":0,"y":0,"curve":"stepped"},{"time":0.8667,"x":0,"y":0,"curve":"stepped"},{"time":1.3333,"x":0,"y":0}]},"start game copy":{"rotate":[{"time":0.1667,"angle":0,"curve":"stepped"},{"time":0.2667,"angle":0,"curve":"stepped"},{"time":0.3333,"angle":0,"curve":"stepped"},{"time":0.4,"angle":0}],"translate":[{"time":0.1667,"x":0,"y":0,"curve":"stepped"},{"time":0.2667,"x":0,"y":0,"curve":"stepped"},{"time":0.3333,"x":0,"y":0,"curve":"stepped"},{"time":0.4,"x":0,"y":0}],"scale":[{"time":0.1667,"x":1.944,"y":1.944},{"time":0.2667,"x":1,"y":1},{"time":0.3333,"x":1.233,"y":1.233},{"time":0.4,"x":1,"y":1}],"shear":[{"time":0.1667,"x":0,"y":0,"curve":"stepped"},{"time":0.2667,"x":0,"y":0,"curve":"stepped"},{"time":0.3333,"x":0,"y":0,"curve":"stepped"},{"time":0.4,"x":0,"y":0}]}}}}}