{"skeleton":{"hash":"K6LUqK2fsLZFUhwcDwwQ+lINS9U","spine":"3.6.53","width":1280,"height":721.01,"images":"./0441/"},"bones":[{"name":"root"},{"name":"0","parent":"root","y":-43.26},{"name":"TONG","parent":"root","x":-9.96},{"name":"TEXTTT","parent":"TONG","y":102.55},{"name":"A","parent":"TEXTTT","x":-80.84,"y":-3.22},{"name":"CHIP","parent":"root","y":-128.51,"scaleX":1.55,"scaleY":1.55},{"name":"CHIP2","parent":"root","y":-128.51,"scaleX":1.55,"scaleY":1.55},{"name":"CHIP3","parent":"root","y":-128.51,"scaleX":1.55,"scaleY":1.55},{"name":"CHIP4","parent":"root","y":-128.51,"scaleX":1.55,"scaleY":1.55},{"name":"CHIP5","parent":"root","y":-128.51,"scaleX":1.55,"scaleY":1.55},{"name":"E","parent":"TEXTTT","x":-248.25,"y":-4.13},{"name":"G","parent":"TEXTTT","x":-170.72,"y":-0.48},{"name":"I","parent":"TEXTTT","x":192.51,"y":1.34},{"name":"LEN","parent":"root","scaleX":3.2,"scaleY":3.2},{"name":"LEN2","parent":"root","scaleX":3.2,"scaleY":3.2},{"name":"LEN3","parent":"root","scaleX":3.2,"scaleY":3.2},{"name":"LEN4","parent":"root","scaleX":3.2,"scaleY":3.2},{"name":"LEN5","parent":"root","scaleX":3.2,"scaleY":3.2},{"name":"LEN6","parent":"root","scaleX":3.2,"scaleY":3.2},{"name":"LEN7","parent":"root","scaleX":3.2,"scaleY":3.2},{"name":"LEN8","parent":"root","scaleX":3.2,"scaleY":3.2},{"name":"LEN9","parent":"root","scaleX":3.2,"scaleY":3.2},{"name":"LEN10","parent":"root","scaleX":3.2,"scaleY":3.2},{"name":"LEN11","parent":"root","scaleX":3.2,"scaleY":3.2},{"name":"M","parent":"TEXTTT","x":-382.54,"y":-4.13},{"name":"N","parent":"TEXTTT","x":264.63,"y":-0.48},{"name":"W","parent":"TEXTTT","x":92.08,"y":2.26},{"name":"bone","parent":"root"},{"name":"q","parent":"0","x":-12.17,"y":-52.33}],"slots":[{"name":"len/1P_00000","bone":"LEN","attachment":"len/1P_00024"},{"name":"len/1P_0","bone":"LEN2","attachment":"len/1P_00024"},{"name":"len/1P_1","bone":"LEN3","attachment":"len/1P_00024"},{"name":"len/1P_2","bone":"LEN4","attachment":"len/1P_00024"},{"name":"len/1P_3","bone":"LEN5","attachment":"len/1P_00024"},{"name":"len/1P_4","bone":"LEN6","attachment":"len/1P_00024"},{"name":"len/1P_5","bone":"LEN7","attachment":"len/1P_00024"},{"name":"len/1P_6","bone":"LEN8","attachment":"len/1P_00024"},{"name":"len/1P_7","bone":"LEN9","attachment":"len/1P_00024"},{"name":"len/1P_8","bone":"LEN10","attachment":"len/1P_00024"},{"name":"len/1P_9","bone":"LEN11","attachment":"len/1P_00024"},{"name":"Group 5","bone":"q","attachment":"Group 5"},{"name":"Group 6","bone":"q","attachment":"Group 5"},{"name":"chi/chi_00000","bone":"CHIP","attachment":"chi/chi_00011"},{"name":"chi/chi_0","bone":"CHIP2","attachment":"chi/chi_00011"},{"name":"chi/chi_1","bone":"CHIP3","attachment":"chi/chi_00011"},{"name":"chi/chi_2","bone":"CHIP4","attachment":"chi/chi_00011"},{"name":"chi/chi_3","bone":"CHIP5","attachment":"chi/chi_00011"},{"name":"A","bone":"A","attachment":"G2"},{"name":"E","bone":"E","attachment":"B2"},{"name":"G","bone":"G","attachment":"I"},{"name":"I","bone":"I","attachment":"I"},{"name":"M","bone":"M","attachment":"M"},{"name":"N","bone":"N","attachment":"N"},{"name":"W","bone":"W","attachment":"W"},{"name":"00_00005","bone":"bone","attachment":"00_00005"}],"skins":{"default":{"00_00005":{"00_00005":{"width":281,"height":281}},"A":{"A":{"x":4.63,"y":1.59,"width":144,"height":146},"G2":{"x":4.63,"y":1.59,"width":152,"height":149}},"E":{"B2":{"x":5.35,"y":2.5,"width":117,"height":146},"E":{"x":5.35,"y":2.5,"width":98,"height":146}},"G":{"G":{"x":1.49,"y":-1.15,"width":152,"height":150},"I":{"x":1.49,"y":-1.15,"width":65,"height":146}},"Group 5":{"Group 5":{"x":-187.49,"y":2.81,"width":393,"height":218}},"Group 6":{"Group 5":{"x":205.54,"y":2.81,"scaleX":-1,"width":393,"height":218}},"I":{"I":{"x":-1.75,"y":-2.97,"width":65,"height":146}},"M":{"M":{"x":-0.02,"y":2.5,"width":153,"height":147}},"N":{"N":{"x":6.89,"y":-1.15,"width":129,"height":146}},"W":{"W":{"x":0.61,"y":-3.89,"width":175,"height":147}},"chi/chi_0":{"chi/chi_00001":{"width":152,"height":300},"chi/chi_00002":{"width":224,"height":300},"chi/chi_00003":{"width":278,"height":300},"chi/chi_00004":{"width":302,"height":300},"chi/chi_00005":{"width":343,"height":300},"chi/chi_00006":{"width":280,"height":300},"chi/chi_00007":{"width":322,"height":300},"chi/chi_00008":{"width":428,"height":300},"chi/chi_00009":{"width":452,"height":300},"chi/chi_00010":{"width":488,"height":300},"chi/chi_00011":{"width":443,"height":300},"chi/chi_00012":{"width":546,"height":300},"chi/chi_00013":{"width":584,"height":300},"chi/chi_00014":{"width":604,"height":300},"chi/chi_00015":{"width":634,"height":300},"chi/chi_00016":{"width":618,"height":300},"chi/chi_00017":{"width":696,"height":300},"chi/chi_00018":{"width":732,"height":300},"chi/chi_00019":{"width":758,"height":300},"chi/chi_00020":{"width":752,"height":300},"chi/chi_00021":{"width":896,"height":300},"chi/chi_00022":{"width":896,"height":300},"chi/chi_00023":{"width":896,"height":300},"chi/chi_00024":{"width":896,"height":300},"chi/chi_00025":{"width":896,"height":300},"chi/chi_00026":{"width":896,"height":300},"chi/chi_00027":{"width":896,"height":300},"chi/chi_00028":{"width":896,"height":300},"chi/chi_00029":{"width":896,"height":300}},"chi/chi_00000":{"chi/chi_00001":{"width":152,"height":300},"chi/chi_00002":{"width":224,"height":300},"chi/chi_00003":{"width":278,"height":300},"chi/chi_00004":{"width":302,"height":300},"chi/chi_00005":{"width":343,"height":300},"chi/chi_00006":{"width":280,"height":300},"chi/chi_00007":{"width":322,"height":300},"chi/chi_00008":{"width":428,"height":300},"chi/chi_00009":{"width":452,"height":300},"chi/chi_00010":{"width":488,"height":300},"chi/chi_00011":{"width":443,"height":300},"chi/chi_00012":{"width":546,"height":300},"chi/chi_00013":{"width":584,"height":300},"chi/chi_00014":{"width":604,"height":300},"chi/chi_00015":{"width":634,"height":300},"chi/chi_00016":{"width":618,"height":300},"chi/chi_00017":{"width":696,"height":300},"chi/chi_00018":{"width":732,"height":300},"chi/chi_00019":{"width":758,"height":300},"chi/chi_00020":{"width":752,"height":300},"chi/chi_00021":{"width":896,"height":300},"chi/chi_00022":{"width":896,"height":300},"chi/chi_00023":{"width":896,"height":300},"chi/chi_00024":{"width":896,"height":300},"chi/chi_00025":{"width":896,"height":300},"chi/chi_00026":{"width":896,"height":300},"chi/chi_00027":{"width":896,"height":300},"chi/chi_00028":{"width":896,"height":300},"chi/chi_00029":{"width":896,"height":300}},"chi/chi_1":{"chi/chi_00001":{"width":152,"height":300},"chi/chi_00002":{"width":224,"height":300},"chi/chi_00003":{"width":278,"height":300},"chi/chi_00004":{"width":302,"height":300},"chi/chi_00005":{"width":343,"height":300},"chi/chi_00006":{"width":280,"height":300},"chi/chi_00007":{"width":322,"height":300},"chi/chi_00008":{"width":428,"height":300},"chi/chi_00009":{"width":452,"height":300},"chi/chi_00010":{"width":488,"height":300},"chi/chi_00011":{"width":443,"height":300},"chi/chi_00012":{"width":546,"height":300},"chi/chi_00013":{"width":584,"height":300},"chi/chi_00014":{"width":604,"height":300},"chi/chi_00015":{"width":634,"height":300},"chi/chi_00016":{"width":618,"height":300},"chi/chi_00017":{"width":696,"height":300},"chi/chi_00018":{"width":732,"height":300},"chi/chi_00019":{"width":758,"height":300},"chi/chi_00020":{"width":752,"height":300},"chi/chi_00021":{"width":896,"height":300},"chi/chi_00022":{"width":896,"height":300},"chi/chi_00023":{"width":896,"height":300},"chi/chi_00024":{"width":896,"height":300},"chi/chi_00025":{"width":896,"height":300},"chi/chi_00026":{"width":896,"height":300},"chi/chi_00027":{"width":896,"height":300},"chi/chi_00028":{"width":896,"height":300},"chi/chi_00029":{"width":896,"height":300}},"chi/chi_2":{"chi/chi_00001":{"width":152,"height":300},"chi/chi_00002":{"width":224,"height":300},"chi/chi_00003":{"width":278,"height":300},"chi/chi_00004":{"width":302,"height":300},"chi/chi_00005":{"width":343,"height":300},"chi/chi_00006":{"width":280,"height":300},"chi/chi_00007":{"width":322,"height":300},"chi/chi_00008":{"width":428,"height":300},"chi/chi_00009":{"width":452,"height":300},"chi/chi_00010":{"width":488,"height":300},"chi/chi_00011":{"width":443,"height":300},"chi/chi_00012":{"width":546,"height":300},"chi/chi_00013":{"width":584,"height":300},"chi/chi_00014":{"width":604,"height":300},"chi/chi_00015":{"width":634,"height":300},"chi/chi_00016":{"width":618,"height":300},"chi/chi_00017":{"width":696,"height":300},"chi/chi_00018":{"width":732,"height":300},"chi/chi_00019":{"width":758,"height":300},"chi/chi_00020":{"width":752,"height":300},"chi/chi_00021":{"width":896,"height":300},"chi/chi_00022":{"width":896,"height":300},"chi/chi_00023":{"width":896,"height":300},"chi/chi_00024":{"width":896,"height":300},"chi/chi_00025":{"width":896,"height":300},"chi/chi_00026":{"width":896,"height":300},"chi/chi_00027":{"width":896,"height":300},"chi/chi_00028":{"width":896,"height":300},"chi/chi_00029":{"width":896,"height":300}},"chi/chi_3":{"chi/chi_00001":{"width":152,"height":300},"chi/chi_00002":{"width":224,"height":300},"chi/chi_00003":{"width":278,"height":300},"chi/chi_00004":{"width":302,"height":300},"chi/chi_00005":{"width":343,"height":300},"chi/chi_00006":{"width":280,"height":300},"chi/chi_00007":{"width":322,"height":300},"chi/chi_00008":{"width":428,"height":300},"chi/chi_00009":{"width":452,"height":300},"chi/chi_00010":{"width":488,"height":300},"chi/chi_00011":{"width":443,"height":300},"chi/chi_00012":{"width":546,"height":300},"chi/chi_00013":{"width":584,"height":300},"chi/chi_00014":{"width":604,"height":300},"chi/chi_00015":{"width":634,"height":300},"chi/chi_00016":{"width":618,"height":300},"chi/chi_00017":{"width":696,"height":300},"chi/chi_00018":{"width":732,"height":300},"chi/chi_00019":{"width":758,"height":300},"chi/chi_00020":{"width":752,"height":300},"chi/chi_00021":{"width":896,"height":300},"chi/chi_00022":{"width":896,"height":300},"chi/chi_00023":{"width":896,"height":300},"chi/chi_00024":{"width":896,"height":300},"chi/chi_00025":{"width":896,"height":300},"chi/chi_00026":{"width":896,"height":300},"chi/chi_00027":{"width":896,"height":300},"chi/chi_00028":{"width":896,"height":300},"chi/chi_00029":{"width":896,"height":300}},"len/1P_0":{"len/1P_00000":{"width":400,"height":225},"len/1P_00001":{"width":400,"height":225},"len/1P_00002":{"width":400,"height":225},"len/1P_00003":{"width":400,"height":225},"len/1P_00004":{"width":400,"height":225},"len/1P_00005":{"width":400,"height":225},"len/1P_00006":{"width":400,"height":225},"len/1P_00007":{"width":400,"height":225},"len/1P_00008":{"width":400,"height":225},"len/1P_00009":{"width":400,"height":225},"len/1P_00010":{"width":400,"height":225},"len/1P_00011":{"width":400,"height":225},"len/1P_00012":{"width":400,"height":225},"len/1P_00013":{"width":400,"height":225},"len/1P_00014":{"width":400,"height":225},"len/1P_00015":{"width":400,"height":225},"len/1P_00016":{"width":400,"height":225},"len/1P_00017":{"width":400,"height":225},"len/1P_00018":{"width":400,"height":225},"len/1P_00019":{"width":400,"height":225},"len/1P_00020":{"width":400,"height":225},"len/1P_00021":{"width":400,"height":225},"len/1P_00022":{"width":400,"height":225},"len/1P_00023":{"width":400,"height":225},"len/1P_00024":{"width":400,"height":225}},"len/1P_00000":{"len/1P_00000":{"width":400,"height":225},"len/1P_00001":{"width":400,"height":225},"len/1P_00002":{"width":400,"height":225},"len/1P_00003":{"width":400,"height":225},"len/1P_00004":{"width":400,"height":225},"len/1P_00005":{"width":400,"height":225},"len/1P_00006":{"width":400,"height":225},"len/1P_00007":{"width":400,"height":225},"len/1P_00008":{"width":400,"height":225},"len/1P_00009":{"width":400,"height":225},"len/1P_00010":{"width":400,"height":225},"len/1P_00011":{"width":400,"height":225},"len/1P_00012":{"width":400,"height":225},"len/1P_00013":{"width":400,"height":225},"len/1P_00014":{"width":400,"height":225},"len/1P_00015":{"width":400,"height":225},"len/1P_00016":{"width":400,"height":225},"len/1P_00017":{"width":400,"height":225},"len/1P_00018":{"width":400,"height":225},"len/1P_00019":{"width":400,"height":225},"len/1P_00020":{"width":400,"height":225},"len/1P_00021":{"width":400,"height":225},"len/1P_00022":{"width":400,"height":225},"len/1P_00023":{"width":400,"height":225},"len/1P_00024":{"width":400,"height":225}},"len/1P_1":{"len/1P_00000":{"width":400,"height":225},"len/1P_00001":{"width":400,"height":225},"len/1P_00002":{"width":400,"height":225},"len/1P_00003":{"width":400,"height":225},"len/1P_00004":{"width":400,"height":225},"len/1P_00005":{"width":400,"height":225},"len/1P_00006":{"width":400,"height":225},"len/1P_00007":{"width":400,"height":225},"len/1P_00008":{"width":400,"height":225},"len/1P_00009":{"width":400,"height":225},"len/1P_00010":{"width":400,"height":225},"len/1P_00011":{"width":400,"height":225},"len/1P_00012":{"width":400,"height":225},"len/1P_00013":{"width":400,"height":225},"len/1P_00014":{"width":400,"height":225},"len/1P_00015":{"width":400,"height":225},"len/1P_00016":{"width":400,"height":225},"len/1P_00017":{"width":400,"height":225},"len/1P_00018":{"width":400,"height":225},"len/1P_00019":{"width":400,"height":225},"len/1P_00020":{"width":400,"height":225},"len/1P_00021":{"width":400,"height":225},"len/1P_00022":{"width":400,"height":225},"len/1P_00023":{"width":400,"height":225},"len/1P_00024":{"width":400,"height":225}},"len/1P_2":{"len/1P_00000":{"width":400,"height":225},"len/1P_00001":{"width":400,"height":225},"len/1P_00002":{"width":400,"height":225},"len/1P_00003":{"width":400,"height":225},"len/1P_00004":{"width":400,"height":225},"len/1P_00005":{"width":400,"height":225},"len/1P_00006":{"width":400,"height":225},"len/1P_00007":{"width":400,"height":225},"len/1P_00008":{"width":400,"height":225},"len/1P_00009":{"width":400,"height":225},"len/1P_00010":{"width":400,"height":225},"len/1P_00011":{"width":400,"height":225},"len/1P_00012":{"width":400,"height":225},"len/1P_00013":{"width":400,"height":225},"len/1P_00014":{"width":400,"height":225},"len/1P_00015":{"width":400,"height":225},"len/1P_00016":{"width":400,"height":225},"len/1P_00017":{"width":400,"height":225},"len/1P_00018":{"width":400,"height":225},"len/1P_00019":{"width":400,"height":225},"len/1P_00020":{"width":400,"height":225},"len/1P_00021":{"width":400,"height":225},"len/1P_00022":{"width":400,"height":225},"len/1P_00023":{"width":400,"height":225},"len/1P_00024":{"width":400,"height":225}},"len/1P_3":{"len/1P_00000":{"width":400,"height":225},"len/1P_00001":{"width":400,"height":225},"len/1P_00002":{"width":400,"height":225},"len/1P_00003":{"width":400,"height":225},"len/1P_00004":{"width":400,"height":225},"len/1P_00005":{"width":400,"height":225},"len/1P_00006":{"width":400,"height":225},"len/1P_00007":{"width":400,"height":225},"len/1P_00008":{"width":400,"height":225},"len/1P_00009":{"width":400,"height":225},"len/1P_00010":{"width":400,"height":225},"len/1P_00011":{"width":400,"height":225},"len/1P_00012":{"width":400,"height":225},"len/1P_00013":{"width":400,"height":225},"len/1P_00014":{"width":400,"height":225},"len/1P_00015":{"width":400,"height":225},"len/1P_00016":{"width":400,"height":225},"len/1P_00017":{"width":400,"height":225},"len/1P_00018":{"width":400,"height":225},"len/1P_00019":{"width":400,"height":225},"len/1P_00020":{"width":400,"height":225},"len/1P_00021":{"width":400,"height":225},"len/1P_00022":{"width":400,"height":225},"len/1P_00023":{"width":400,"height":225},"len/1P_00024":{"width":400,"height":225}},"len/1P_4":{"len/1P_00000":{"width":400,"height":225},"len/1P_00001":{"width":400,"height":225},"len/1P_00002":{"width":400,"height":225},"len/1P_00003":{"width":400,"height":225},"len/1P_00004":{"width":400,"height":225},"len/1P_00005":{"width":400,"height":225},"len/1P_00006":{"width":400,"height":225},"len/1P_00007":{"width":400,"height":225},"len/1P_00008":{"width":400,"height":225},"len/1P_00009":{"width":400,"height":225},"len/1P_00010":{"width":400,"height":225},"len/1P_00011":{"width":400,"height":225},"len/1P_00012":{"width":400,"height":225},"len/1P_00013":{"width":400,"height":225},"len/1P_00014":{"width":400,"height":225},"len/1P_00015":{"width":400,"height":225},"len/1P_00016":{"width":400,"height":225},"len/1P_00017":{"width":400,"height":225},"len/1P_00018":{"width":400,"height":225},"len/1P_00019":{"width":400,"height":225},"len/1P_00020":{"width":400,"height":225},"len/1P_00021":{"width":400,"height":225},"len/1P_00022":{"width":400,"height":225},"len/1P_00023":{"width":400,"height":225},"len/1P_00024":{"width":400,"height":225}},"len/1P_5":{"len/1P_00000":{"width":400,"height":225},"len/1P_00001":{"width":400,"height":225},"len/1P_00002":{"width":400,"height":225},"len/1P_00003":{"width":400,"height":225},"len/1P_00004":{"width":400,"height":225},"len/1P_00005":{"width":400,"height":225},"len/1P_00006":{"width":400,"height":225},"len/1P_00007":{"width":400,"height":225},"len/1P_00008":{"width":400,"height":225},"len/1P_00009":{"width":400,"height":225},"len/1P_00010":{"width":400,"height":225},"len/1P_00011":{"width":400,"height":225},"len/1P_00012":{"width":400,"height":225},"len/1P_00013":{"width":400,"height":225},"len/1P_00014":{"width":400,"height":225},"len/1P_00015":{"width":400,"height":225},"len/1P_00016":{"width":400,"height":225},"len/1P_00017":{"width":400,"height":225},"len/1P_00018":{"width":400,"height":225},"len/1P_00019":{"width":400,"height":225},"len/1P_00020":{"width":400,"height":225},"len/1P_00021":{"width":400,"height":225},"len/1P_00022":{"width":400,"height":225},"len/1P_00023":{"width":400,"height":225},"len/1P_00024":{"width":400,"height":225}},"len/1P_6":{"len/1P_00000":{"width":400,"height":225},"len/1P_00001":{"width":400,"height":225},"len/1P_00002":{"width":400,"height":225},"len/1P_00003":{"width":400,"height":225},"len/1P_00004":{"width":400,"height":225},"len/1P_00005":{"width":400,"height":225},"len/1P_00006":{"width":400,"height":225},"len/1P_00007":{"width":400,"height":225},"len/1P_00008":{"width":400,"height":225},"len/1P_00009":{"width":400,"height":225},"len/1P_00010":{"width":400,"height":225},"len/1P_00011":{"width":400,"height":225},"len/1P_00012":{"width":400,"height":225},"len/1P_00013":{"width":400,"height":225},"len/1P_00014":{"width":400,"height":225},"len/1P_00015":{"width":400,"height":225},"len/1P_00016":{"width":400,"height":225},"len/1P_00017":{"width":400,"height":225},"len/1P_00018":{"width":400,"height":225},"len/1P_00019":{"width":400,"height":225},"len/1P_00020":{"width":400,"height":225},"len/1P_00021":{"width":400,"height":225},"len/1P_00022":{"width":400,"height":225},"len/1P_00023":{"width":400,"height":225},"len/1P_00024":{"width":400,"height":225}},"len/1P_7":{"len/1P_00000":{"width":400,"height":225},"len/1P_00001":{"width":400,"height":225},"len/1P_00002":{"width":400,"height":225},"len/1P_00003":{"width":400,"height":225},"len/1P_00004":{"width":400,"height":225},"len/1P_00005":{"width":400,"height":225},"len/1P_00006":{"width":400,"height":225},"len/1P_00007":{"width":400,"height":225},"len/1P_00008":{"width":400,"height":225},"len/1P_00009":{"width":400,"height":225},"len/1P_00010":{"width":400,"height":225},"len/1P_00011":{"width":400,"height":225},"len/1P_00012":{"width":400,"height":225},"len/1P_00013":{"width":400,"height":225},"len/1P_00014":{"width":400,"height":225},"len/1P_00015":{"width":400,"height":225},"len/1P_00016":{"width":400,"height":225},"len/1P_00017":{"width":400,"height":225},"len/1P_00018":{"width":400,"height":225},"len/1P_00019":{"width":400,"height":225},"len/1P_00020":{"width":400,"height":225},"len/1P_00021":{"width":400,"height":225},"len/1P_00022":{"width":400,"height":225},"len/1P_00023":{"width":400,"height":225},"len/1P_00024":{"width":400,"height":225}},"len/1P_8":{"len/1P_00000":{"width":400,"height":225},"len/1P_00001":{"width":400,"height":225},"len/1P_00002":{"width":400,"height":225},"len/1P_00003":{"width":400,"height":225},"len/1P_00004":{"width":400,"height":225},"len/1P_00005":{"width":400,"height":225},"len/1P_00006":{"width":400,"height":225},"len/1P_00007":{"width":400,"height":225},"len/1P_00008":{"width":400,"height":225},"len/1P_00009":{"width":400,"height":225},"len/1P_00010":{"width":400,"height":225},"len/1P_00011":{"width":400,"height":225},"len/1P_00012":{"width":400,"height":225},"len/1P_00013":{"width":400,"height":225},"len/1P_00014":{"width":400,"height":225},"len/1P_00015":{"width":400,"height":225},"len/1P_00016":{"width":400,"height":225},"len/1P_00017":{"width":400,"height":225},"len/1P_00018":{"width":400,"height":225},"len/1P_00019":{"width":400,"height":225},"len/1P_00020":{"width":400,"height":225},"len/1P_00021":{"width":400,"height":225},"len/1P_00022":{"width":400,"height":225},"len/1P_00023":{"width":400,"height":225},"len/1P_00024":{"width":400,"height":225}},"len/1P_9":{"len/1P_00000":{"width":400,"height":225},"len/1P_00001":{"width":400,"height":225},"len/1P_00002":{"width":400,"height":225},"len/1P_00003":{"width":400,"height":225},"len/1P_00004":{"width":400,"height":225},"len/1P_00005":{"width":400,"height":225},"len/1P_00006":{"width":400,"height":225},"len/1P_00007":{"width":400,"height":225},"len/1P_00008":{"width":400,"height":225},"len/1P_00009":{"width":400,"height":225},"len/1P_00010":{"width":400,"height":225},"len/1P_00011":{"width":400,"height":225},"len/1P_00012":{"width":400,"height":225},"len/1P_00013":{"width":400,"height":225},"len/1P_00014":{"width":400,"height":225},"len/1P_00015":{"width":400,"height":225},"len/1P_00016":{"width":400,"height":225},"len/1P_00017":{"width":400,"height":225},"len/1P_00018":{"width":400,"height":225},"len/1P_00019":{"width":400,"height":225},"len/1P_00020":{"width":400,"height":225},"len/1P_00021":{"width":400,"height":225},"len/1P_00022":{"width":400,"height":225},"len/1P_00023":{"width":400,"height":225},"len/1P_00024":{"width":400,"height":225}}}},"animations":{"bigwin":{"slots":{"00_00005":{"color":[{"time":0,"color":"ffffffff"},{"time":0.3333,"color":"ffffff00"}]},"Group 5":{"color":[{"time":0,"color":"ffffff00","curve":"stepped"},{"time":0.1667,"color":"ffffff00"},{"time":0.3333,"color":"ffffffff","curve":"stepped"},{"time":2.6667,"color":"ffffffff"},{"time":2.8333,"color":"ffffff00"}]},"Group 6":{"color":[{"time":0,"color":"ffffff00","curve":"stepped"},{"time":0.1667,"color":"ffffff00"},{"time":0.3333,"color":"ffffffff","curve":"stepped"},{"time":2.6667,"color":"ffffffff"},{"time":2.8333,"color":"ffffff00"}]},"M":{"color":[{"time":0,"color":"ffffff00"}]},"chi/chi_00000":{"color":[{"time":0.8,"color":"ffffffff"},{"time":0.9667,"color":"ffffff0d"}],"attachment":[{"time":0.0333,"name":"chi/chi_00001"},{"time":0.0667,"name":"chi/chi_00002"},{"time":0.1,"name":"chi/chi_00003"},{"time":0.1333,"name":"chi/chi_00004"},{"time":0.1667,"name":"chi/chi_00005"},{"time":0.2,"name":"chi/chi_00006"},{"time":0.2333,"name":"chi/chi_00007"},{"time":0.2667,"name":"chi/chi_00008"},{"time":0.3,"name":"chi/chi_00009"},{"time":0.3333,"name":"chi/chi_00010"},{"time":0.3667,"name":"chi/chi_00011"},{"time":0.4,"name":"chi/chi_00012"},{"time":0.4333,"name":"chi/chi_00013"},{"time":0.4667,"name":"chi/chi_00014"},{"time":0.5,"name":"chi/chi_00015"},{"time":0.5333,"name":"chi/chi_00016"},{"time":0.5667,"name":"chi/chi_00017"},{"time":0.6,"name":"chi/chi_00018"},{"time":0.6333,"name":"chi/chi_00019"},{"time":0.6667,"name":"chi/chi_00020"},{"time":0.7,"name":"chi/chi_00021"},{"time":0.7333,"name":"chi/chi_00022"},{"time":0.7667,"name":"chi/chi_00023"},{"time":0.8,"name":"chi/chi_00024"},{"time":0.8333,"name":"chi/chi_00025"},{"time":0.8667,"name":"chi/chi_00026"},{"time":0.9,"name":"chi/chi_00027"},{"time":0.9333,"name":"chi/chi_00028"},{"time":0.9667,"name":"chi/chi_00029"}]},"chi/chi_0":{"color":[{"time":1.0333,"color":"ffffffff"},{"time":1.4667,"color":"ffffff0d"}],"attachment":[{"time":0,"name":null},{"time":0.5333,"name":"chi/chi_00001"},{"time":0.5667,"name":"chi/chi_00002"},{"time":0.6,"name":"chi/chi_00003"},{"time":0.6333,"name":"chi/chi_00004"},{"time":0.6667,"name":"chi/chi_00005"},{"time":0.7,"name":"chi/chi_00006"},{"time":0.7333,"name":"chi/chi_00007"},{"time":0.7667,"name":"chi/chi_00008"},{"time":0.8,"name":"chi/chi_00009"},{"time":0.8333,"name":"chi/chi_00010"},{"time":0.8667,"name":"chi/chi_00011"},{"time":0.9,"name":"chi/chi_00012"},{"time":0.9333,"name":"chi/chi_00013"},{"time":0.9667,"name":"chi/chi_00014"},{"time":1,"name":"chi/chi_00015"},{"time":1.0333,"name":"chi/chi_00016"},{"time":1.0667,"name":"chi/chi_00017"},{"time":1.1,"name":"chi/chi_00018"},{"time":1.1333,"name":"chi/chi_00019"},{"time":1.1667,"name":"chi/chi_00020"},{"time":1.2,"name":"chi/chi_00021"},{"time":1.2333,"name":"chi/chi_00022"},{"time":1.2667,"name":"chi/chi_00023"},{"time":1.3,"name":"chi/chi_00024"},{"time":1.3333,"name":"chi/chi_00025"},{"time":1.3667,"name":"chi/chi_00026"},{"time":1.4,"name":"chi/chi_00027"},{"time":1.4333,"name":"chi/chi_00028"},{"time":1.4667,"name":"chi/chi_00029"}]},"chi/chi_1":{"color":[{"time":1.5333,"color":"ffffffff"},{"time":1.9667,"color":"ffffff0d"}],"attachment":[{"time":0,"name":null},{"time":1.0333,"name":"chi/chi_00001"},{"time":1.0667,"name":"chi/chi_00002"},{"time":1.1,"name":"chi/chi_00003"},{"time":1.1333,"name":"chi/chi_00004"},{"time":1.1667,"name":"chi/chi_00005"},{"time":1.2,"name":"chi/chi_00006"},{"time":1.2333,"name":"chi/chi_00007"},{"time":1.2667,"name":"chi/chi_00008"},{"time":1.3,"name":"chi/chi_00009"},{"time":1.3333,"name":"chi/chi_00010"},{"time":1.3667,"name":"chi/chi_00011"},{"time":1.4,"name":"chi/chi_00012"},{"time":1.4333,"name":"chi/chi_00013"},{"time":1.4667,"name":"chi/chi_00014"},{"time":1.5,"name":"chi/chi_00015"},{"time":1.5333,"name":"chi/chi_00016"},{"time":1.5667,"name":"chi/chi_00017"},{"time":1.6,"name":"chi/chi_00018"},{"time":1.6333,"name":"chi/chi_00019"},{"time":1.6667,"name":"chi/chi_00020"},{"time":1.7,"name":"chi/chi_00021"},{"time":1.7333,"name":"chi/chi_00022"},{"time":1.7667,"name":"chi/chi_00023"},{"time":1.8,"name":"chi/chi_00024"},{"time":1.8333,"name":"chi/chi_00025"},{"time":1.8667,"name":"chi/chi_00026"},{"time":1.9,"name":"chi/chi_00027"},{"time":1.9333,"name":"chi/chi_00028"},{"time":1.9667,"name":"chi/chi_00029"}]},"chi/chi_2":{"color":[{"time":2.1,"color":"ffffffff"},{"time":2.4667,"color":"ffffff0d"}],"attachment":[{"time":0,"name":null},{"time":1.5333,"name":"chi/chi_00001"},{"time":1.5667,"name":"chi/chi_00002"},{"time":1.6,"name":"chi/chi_00003"},{"time":1.6333,"name":"chi/chi_00004"},{"time":1.6667,"name":"chi/chi_00005"},{"time":1.7,"name":"chi/chi_00006"},{"time":1.7333,"name":"chi/chi_00007"},{"time":1.7667,"name":"chi/chi_00008"},{"time":1.8,"name":"chi/chi_00009"},{"time":1.8333,"name":"chi/chi_00010"},{"time":1.8667,"name":"chi/chi_00011"},{"time":1.9,"name":"chi/chi_00012"},{"time":1.9333,"name":"chi/chi_00013"},{"time":1.9667,"name":"chi/chi_00014"},{"time":2,"name":"chi/chi_00015"},{"time":2.0333,"name":"chi/chi_00016"},{"time":2.0667,"name":"chi/chi_00017"},{"time":2.1,"name":"chi/chi_00018"},{"time":2.1333,"name":"chi/chi_00019"},{"time":2.1667,"name":"chi/chi_00020"},{"time":2.2,"name":"chi/chi_00021"},{"time":2.2333,"name":"chi/chi_00022"},{"time":2.2667,"name":"chi/chi_00023"},{"time":2.3,"name":"chi/chi_00024"},{"time":2.3333,"name":"chi/chi_00025"},{"time":2.3667,"name":"chi/chi_00026"},{"time":2.4,"name":"chi/chi_00027"},{"time":2.4333,"name":"chi/chi_00028"},{"time":2.4667,"name":"chi/chi_00029"}]},"chi/chi_3":{"color":[{"time":2.4667,"color":"ffffffff"},{"time":2.8333,"color":"ffffff0d"}],"attachment":[{"time":0,"name":null},{"time":1.9,"name":"chi/chi_00001"},{"time":1.9333,"name":"chi/chi_00002"},{"time":1.9667,"name":"chi/chi_00003"},{"time":2,"name":"chi/chi_00004"},{"time":2.0333,"name":"chi/chi_00005"},{"time":2.0667,"name":"chi/chi_00006"},{"time":2.1,"name":"chi/chi_00007"},{"time":2.1333,"name":"chi/chi_00008"},{"time":2.1667,"name":"chi/chi_00009"},{"time":2.2,"name":"chi/chi_00010"},{"time":2.2333,"name":"chi/chi_00011"},{"time":2.2667,"name":"chi/chi_00012"},{"time":2.3,"name":"chi/chi_00013"},{"time":2.3333,"name":"chi/chi_00014"},{"time":2.3667,"name":"chi/chi_00015"},{"time":2.4,"name":"chi/chi_00016"},{"time":2.4333,"name":"chi/chi_00017"},{"time":2.4667,"name":"chi/chi_00018"},{"time":2.5,"name":"chi/chi_00019"},{"time":2.5333,"name":"chi/chi_00020"},{"time":2.5667,"name":"chi/chi_00021"},{"time":2.6,"name":"chi/chi_00022"},{"time":2.6333,"name":"chi/chi_00023"},{"time":2.6667,"name":"chi/chi_00024"},{"time":2.7,"name":"chi/chi_00025"},{"time":2.7333,"name":"chi/chi_00026"},{"time":2.7667,"name":"chi/chi_00027"},{"time":2.8,"name":"chi/chi_00028"},{"time":2.8333,"name":"chi/chi_00029"}]},"len/1P_00000":{"color":[{"time":0.1667,"color":"ffffff00"},{"time":0.5,"color":"ffffffff","curve":"stepped"},{"time":0.6667,"color":"ffffffff"},{"time":1,"color":"ffffff00"}],"attachment":[{"time":0,"name":null},{"time":0.1667,"name":"len/1P_00000"},{"time":0.2,"name":"len/1P_00001"},{"time":0.2333,"name":"len/1P_00002"},{"time":0.2667,"name":"len/1P_00003"},{"time":0.3,"name":"len/1P_00004"},{"time":0.3333,"name":"len/1P_00005"},{"time":0.3667,"name":"len/1P_00006"},{"time":0.4,"name":"len/1P_00007"},{"time":0.4333,"name":"len/1P_00008"},{"time":0.4667,"name":"len/1P_00009"},{"time":0.5,"name":"len/1P_00010"},{"time":0.5333,"name":"len/1P_00011"},{"time":0.5667,"name":"len/1P_00012"},{"time":0.6,"name":"len/1P_00013"},{"time":0.6333,"name":"len/1P_00014"},{"time":0.6667,"name":"len/1P_00015"},{"time":0.7,"name":"len/1P_00016"},{"time":0.7333,"name":"len/1P_00017"},{"time":0.7667,"name":"len/1P_00018"},{"time":0.8,"name":"len/1P_00019"},{"time":0.8333,"name":"len/1P_00020"},{"time":0.8667,"name":"len/1P_00021"},{"time":0.9,"name":"len/1P_00022"},{"time":0.9333,"name":"len/1P_00023"},{"time":0.9667,"name":"len/1P_00024"},{"time":1,"name":null}]},"len/1P_0":{"color":[{"time":0.5,"color":"ffffff00"},{"time":0.8333,"color":"ffffffff","curve":"stepped"},{"time":1,"color":"ffffffff"},{"time":1.3333,"color":"ffffff00"}],"attachment":[{"time":0,"name":null},{"time":0.5,"name":"len/1P_00000"},{"time":0.5333,"name":"len/1P_00001"},{"time":0.5667,"name":"len/1P_00002"},{"time":0.6,"name":"len/1P_00003"},{"time":0.6333,"name":"len/1P_00004"},{"time":0.6667,"name":"len/1P_00005"},{"time":0.7,"name":"len/1P_00006"},{"time":0.7333,"name":"len/1P_00007"},{"time":0.7667,"name":"len/1P_00008"},{"time":0.8,"name":"len/1P_00009"},{"time":0.8333,"name":"len/1P_00010"},{"time":0.8667,"name":"len/1P_00011"},{"time":0.9,"name":"len/1P_00012"},{"time":0.9333,"name":"len/1P_00013"},{"time":0.9667,"name":"len/1P_00014"},{"time":1,"name":"len/1P_00015"},{"time":1.0333,"name":"len/1P_00016"},{"time":1.0667,"name":"len/1P_00017"},{"time":1.1,"name":"len/1P_00018"},{"time":1.1333,"name":"len/1P_00019"},{"time":1.1667,"name":"len/1P_00020"},{"time":1.2,"name":"len/1P_00021"},{"time":1.2333,"name":"len/1P_00022"},{"time":1.2667,"name":"len/1P_00023"},{"time":1.3,"name":"len/1P_00024"},{"time":1.3333,"name":null}]},"len/1P_1":{"color":[{"time":0.6667,"color":"ffffff00"},{"time":1.0667,"color":"ffffffff"},{"time":1.5,"color":"ffffff00"}],"attachment":[{"time":0,"name":null},{"time":0.6667,"name":"len/1P_00000"},{"time":0.7,"name":"len/1P_00001"},{"time":0.7333,"name":"len/1P_00002"},{"time":0.7667,"name":"len/1P_00003"},{"time":0.8,"name":"len/1P_00004"},{"time":0.8333,"name":"len/1P_00005"},{"time":0.8667,"name":"len/1P_00006"},{"time":0.9,"name":"len/1P_00007"},{"time":0.9333,"name":"len/1P_00008"},{"time":0.9667,"name":"len/1P_00009"},{"time":1,"name":"len/1P_00010"},{"time":1.0333,"name":"len/1P_00011"},{"time":1.0667,"name":"len/1P_00012"},{"time":1.1,"name":"len/1P_00013"},{"time":1.1333,"name":"len/1P_00014"},{"time":1.1667,"name":"len/1P_00015"},{"time":1.2,"name":"len/1P_00016"},{"time":1.2333,"name":"len/1P_00017"},{"time":1.2667,"name":"len/1P_00018"},{"time":1.3,"name":"len/1P_00019"},{"time":1.3333,"name":"len/1P_00020"},{"time":1.3667,"name":"len/1P_00021"},{"time":1.4,"name":"len/1P_00022"},{"time":1.4333,"name":"len/1P_00023"},{"time":1.4667,"name":"len/1P_00024"},{"time":1.5,"name":null}]},"len/1P_2":{"color":[{"time":0.8333,"color":"ffffff00"},{"time":1.2333,"color":"ffffffff"},{"time":1.6667,"color":"ffffff00"}],"attachment":[{"time":0,"name":null},{"time":0.8333,"name":"len/1P_00000"},{"time":0.8667,"name":"len/1P_00001"},{"time":0.9,"name":"len/1P_00002"},{"time":0.9333,"name":"len/1P_00003"},{"time":0.9667,"name":"len/1P_00004"},{"time":1,"name":"len/1P_00005"},{"time":1.0333,"name":"len/1P_00006"},{"time":1.0667,"name":"len/1P_00007"},{"time":1.1,"name":"len/1P_00008"},{"time":1.1333,"name":"len/1P_00009"},{"time":1.1667,"name":"len/1P_00010"},{"time":1.2,"name":"len/1P_00011"},{"time":1.2333,"name":"len/1P_00012"},{"time":1.2667,"name":"len/1P_00013"},{"time":1.3,"name":"len/1P_00014"},{"time":1.3333,"name":"len/1P_00015"},{"time":1.3667,"name":"len/1P_00016"},{"time":1.4,"name":"len/1P_00017"},{"time":1.4333,"name":"len/1P_00018"},{"time":1.4667,"name":"len/1P_00019"},{"time":1.5,"name":"len/1P_00020"},{"time":1.5333,"name":"len/1P_00021"},{"time":1.5667,"name":"len/1P_00022"},{"time":1.6,"name":"len/1P_00023"},{"time":1.6333,"name":"len/1P_00024"},{"time":1.6667,"name":null}]},"len/1P_3":{"color":[{"time":1,"color":"ffffff00"},{"time":1.4,"color":"ffffffff"},{"time":1.8333,"color":"ffffff00"}],"attachment":[{"time":0,"name":null},{"time":1,"name":"len/1P_00000"},{"time":1.0333,"name":"len/1P_00001"},{"time":1.0667,"name":"len/1P_00002"},{"time":1.1,"name":"len/1P_00003"},{"time":1.1333,"name":"len/1P_00004"},{"time":1.1667,"name":"len/1P_00005"},{"time":1.2,"name":"len/1P_00006"},{"time":1.2333,"name":"len/1P_00007"},{"time":1.2667,"name":"len/1P_00008"},{"time":1.3,"name":"len/1P_00009"},{"time":1.3333,"name":"len/1P_00010"},{"time":1.3667,"name":"len/1P_00011"},{"time":1.4,"name":"len/1P_00012"},{"time":1.4333,"name":"len/1P_00013"},{"time":1.4667,"name":"len/1P_00014"},{"time":1.5,"name":"len/1P_00015"},{"time":1.5333,"name":"len/1P_00016"},{"time":1.5667,"name":"len/1P_00017"},{"time":1.6,"name":"len/1P_00018"},{"time":1.6333,"name":"len/1P_00019"},{"time":1.6667,"name":"len/1P_00020"},{"time":1.7,"name":"len/1P_00021"},{"time":1.7333,"name":"len/1P_00022"},{"time":1.7667,"name":"len/1P_00023"},{"time":1.8,"name":"len/1P_00024"},{"time":1.8333,"name":null}]},"len/1P_4":{"color":[{"time":1.1667,"color":"ffffff00"},{"time":1.5667,"color":"ffffffff"},{"time":2,"color":"ffffff00"}],"attachment":[{"time":0,"name":null},{"time":1.1667,"name":"len/1P_00000"},{"time":1.2,"name":"len/1P_00001"},{"time":1.2333,"name":"len/1P_00002"},{"time":1.2667,"name":"len/1P_00003"},{"time":1.3,"name":"len/1P_00004"},{"time":1.3333,"name":"len/1P_00005"},{"time":1.3667,"name":"len/1P_00006"},{"time":1.4,"name":"len/1P_00007"},{"time":1.4333,"name":"len/1P_00008"},{"time":1.4667,"name":"len/1P_00009"},{"time":1.5,"name":"len/1P_00010"},{"time":1.5333,"name":"len/1P_00011"},{"time":1.5667,"name":"len/1P_00012"},{"time":1.6,"name":"len/1P_00013"},{"time":1.6333,"name":"len/1P_00014"},{"time":1.6667,"name":"len/1P_00015"},{"time":1.7,"name":"len/1P_00016"},{"time":1.7333,"name":"len/1P_00017"},{"time":1.7667,"name":"len/1P_00018"},{"time":1.8,"name":"len/1P_00019"},{"time":1.8333,"name":"len/1P_00020"},{"time":1.8667,"name":"len/1P_00021"},{"time":1.9,"name":"len/1P_00022"},{"time":1.9333,"name":"len/1P_00023"},{"time":1.9667,"name":"len/1P_00024"},{"time":2,"name":null}]},"len/1P_5":{"color":[{"time":1.3333,"color":"ffffff00"},{"time":1.7333,"color":"ffffffff"},{"time":2.1667,"color":"ffffff00"}],"attachment":[{"time":0,"name":null},{"time":1.3333,"name":"len/1P_00000"},{"time":1.3667,"name":"len/1P_00001"},{"time":1.4,"name":"len/1P_00002"},{"time":1.4333,"name":"len/1P_00003"},{"time":1.4667,"name":"len/1P_00004"},{"time":1.5,"name":"len/1P_00005"},{"time":1.5333,"name":"len/1P_00006"},{"time":1.5667,"name":"len/1P_00007"},{"time":1.6,"name":"len/1P_00008"},{"time":1.6333,"name":"len/1P_00009"},{"time":1.6667,"name":"len/1P_00010"},{"time":1.7,"name":"len/1P_00011"},{"time":1.7333,"name":"len/1P_00012"},{"time":1.7667,"name":"len/1P_00013"},{"time":1.8,"name":"len/1P_00014"},{"time":1.8333,"name":"len/1P_00015"},{"time":1.8667,"name":"len/1P_00016"},{"time":1.9,"name":"len/1P_00017"},{"time":1.9333,"name":"len/1P_00018"},{"time":1.9667,"name":"len/1P_00019"},{"time":2,"name":"len/1P_00020"},{"time":2.0333,"name":"len/1P_00021"},{"time":2.0667,"name":"len/1P_00022"},{"time":2.1,"name":"len/1P_00023"},{"time":2.1333,"name":"len/1P_00024"},{"time":2.1667,"name":null}]},"len/1P_6":{"color":[{"time":1.5,"color":"ffffff00"},{"time":1.9,"color":"ffffffff"},{"time":2.3333,"color":"ffffff00"}],"attachment":[{"time":0,"name":null},{"time":1.5,"name":"len/1P_00000"},{"time":1.5333,"name":"len/1P_00001"},{"time":1.5667,"name":"len/1P_00002"},{"time":1.6,"name":"len/1P_00003"},{"time":1.6333,"name":"len/1P_00004"},{"time":1.6667,"name":"len/1P_00005"},{"time":1.7,"name":"len/1P_00006"},{"time":1.7333,"name":"len/1P_00007"},{"time":1.7667,"name":"len/1P_00008"},{"time":1.8,"name":"len/1P_00009"},{"time":1.8333,"name":"len/1P_00010"},{"time":1.8667,"name":"len/1P_00011"},{"time":1.9,"name":"len/1P_00012"},{"time":1.9333,"name":"len/1P_00013"},{"time":1.9667,"name":"len/1P_00014"},{"time":2,"name":"len/1P_00015"},{"time":2.0333,"name":"len/1P_00016"},{"time":2.0667,"name":"len/1P_00017"},{"time":2.1,"name":"len/1P_00018"},{"time":2.1333,"name":"len/1P_00019"},{"time":2.1667,"name":"len/1P_00020"},{"time":2.2,"name":"len/1P_00021"},{"time":2.2333,"name":"len/1P_00022"},{"time":2.2667,"name":"len/1P_00023"},{"time":2.3,"name":"len/1P_00024"},{"time":2.3333,"name":null}]},"len/1P_7":{"color":[{"time":1.6667,"color":"ffffff00"},{"time":2.0667,"color":"ffffffff"},{"time":2.5,"color":"ffffff00"}],"attachment":[{"time":0,"name":null},{"time":1.6667,"name":"len/1P_00000"},{"time":1.7,"name":"len/1P_00001"},{"time":1.7333,"name":"len/1P_00002"},{"time":1.7667,"name":"len/1P_00003"},{"time":1.8,"name":"len/1P_00004"},{"time":1.8333,"name":"len/1P_00005"},{"time":1.8667,"name":"len/1P_00006"},{"time":1.9,"name":"len/1P_00007"},{"time":1.9333,"name":"len/1P_00008"},{"time":1.9667,"name":"len/1P_00009"},{"time":2,"name":"len/1P_00010"},{"time":2.0333,"name":"len/1P_00011"},{"time":2.0667,"name":"len/1P_00012"},{"time":2.1,"name":"len/1P_00013"},{"time":2.1333,"name":"len/1P_00014"},{"time":2.1667,"name":"len/1P_00015"},{"time":2.2,"name":"len/1P_00016"},{"time":2.2333,"name":"len/1P_00017"},{"time":2.2667,"name":"len/1P_00018"},{"time":2.3,"name":"len/1P_00019"},{"time":2.3333,"name":"len/1P_00020"},{"time":2.3667,"name":"len/1P_00021"},{"time":2.4,"name":"len/1P_00022"},{"time":2.4333,"name":"len/1P_00023"},{"time":2.4667,"name":"len/1P_00024"},{"time":2.5,"name":null}]},"len/1P_8":{"color":[{"time":1.8333,"color":"ffffff00"},{"time":2.2333,"color":"ffffffff"},{"time":2.6667,"color":"ffffff00"}],"attachment":[{"time":0,"name":null},{"time":1.8333,"name":"len/1P_00000"},{"time":1.8667,"name":"len/1P_00001"},{"time":1.9,"name":"len/1P_00002"},{"time":1.9333,"name":"len/1P_00003"},{"time":1.9667,"name":"len/1P_00004"},{"time":2,"name":"len/1P_00005"},{"time":2.0333,"name":"len/1P_00006"},{"time":2.0667,"name":"len/1P_00007"},{"time":2.1,"name":"len/1P_00008"},{"time":2.1333,"name":"len/1P_00009"},{"time":2.1667,"name":"len/1P_00010"},{"time":2.2,"name":"len/1P_00011"},{"time":2.2333,"name":"len/1P_00012"},{"time":2.2667,"name":"len/1P_00013"},{"time":2.3,"name":"len/1P_00014"},{"time":2.3333,"name":"len/1P_00015"},{"time":2.3667,"name":"len/1P_00016"},{"time":2.4,"name":"len/1P_00017"},{"time":2.4333,"name":"len/1P_00018"},{"time":2.4667,"name":"len/1P_00019"},{"time":2.5,"name":"len/1P_00020"},{"time":2.5333,"name":"len/1P_00021"},{"time":2.5667,"name":"len/1P_00022"},{"time":2.6,"name":"len/1P_00023"},{"time":2.6333,"name":"len/1P_00024"},{"time":2.6667,"name":null}]},"len/1P_9":{"color":[{"time":2,"color":"ffffff00"},{"time":2.4,"color":"ffffffff"},{"time":2.8333,"color":"ffffff00"}],"attachment":[{"time":0,"name":null},{"time":2,"name":"len/1P_00000"},{"time":2.0333,"name":"len/1P_00001"},{"time":2.0667,"name":"len/1P_00002"},{"time":2.1,"name":"len/1P_00003"},{"time":2.1333,"name":"len/1P_00004"},{"time":2.1667,"name":"len/1P_00005"},{"time":2.2,"name":"len/1P_00006"},{"time":2.2333,"name":"len/1P_00007"},{"time":2.2667,"name":"len/1P_00008"},{"time":2.3,"name":"len/1P_00009"},{"time":2.3333,"name":"len/1P_00010"},{"time":2.3667,"name":"len/1P_00011"},{"time":2.4,"name":"len/1P_00012"},{"time":2.4333,"name":"len/1P_00013"},{"time":2.4667,"name":"len/1P_00014"},{"time":2.5,"name":"len/1P_00015"},{"time":2.5333,"name":"len/1P_00016"},{"time":2.5667,"name":"len/1P_00017"},{"time":2.6,"name":"len/1P_00018"},{"time":2.6333,"name":"len/1P_00019"},{"time":2.6667,"name":"len/1P_00020"},{"time":2.7,"name":"len/1P_00021"},{"time":2.7333,"name":"len/1P_00022"},{"time":2.7667,"name":"len/1P_00023"},{"time":2.8,"name":"len/1P_00024"},{"time":2.8333,"name":null}]}},"bones":{"E":{"translate":[{"time":0,"x":248.25,"y":0,"curve":[0.25,0,0.75,1]},{"time":0.1333,"x":0,"y":0,"curve":"stepped"},{"time":2.6667,"x":0,"y":0},{"time":2.8333,"x":248.25,"y":0}],"scale":[{"time":0,"x":0,"y":0,"curve":[0.25,0,0.75,1]},{"time":0.1333,"x":1,"y":1,"curve":"stepped"},{"time":2.6667,"x":1,"y":1},{"time":2.8333,"x":0,"y":0}]},"G":{"translate":[{"time":0,"x":170.72,"y":0,"curve":"stepped"},{"time":0.0667,"x":170.72,"y":0,"curve":[0.25,0,0.75,1]},{"time":0.2,"x":0,"y":0,"curve":"stepped"},{"time":2.6667,"x":0,"y":0},{"time":2.8333,"x":170.72,"y":0}],"scale":[{"time":0,"x":0,"y":0,"curve":"stepped"},{"time":0.0667,"x":0,"y":0,"curve":[0.25,0,0.75,1]},{"time":0.2,"x":1,"y":1,"curve":"stepped"},{"time":2.6667,"x":1,"y":1},{"time":2.8333,"x":0,"y":0}]},"A":{"translate":[{"time":0,"x":80.84,"y":0,"curve":"stepped"},{"time":0.1333,"x":80.84,"y":0,"curve":[0.25,0,0.75,1]},{"time":0.2667,"x":0,"y":0,"curve":"stepped"},{"time":2.6667,"x":0,"y":0},{"time":2.8333,"x":80.84,"y":0}],"scale":[{"time":0,"x":0,"y":0,"curve":"stepped"},{"time":0.1333,"x":0,"y":0,"curve":[0.25,0,0.75,1]},{"time":0.2667,"x":1,"y":1,"curve":"stepped"},{"time":2.6667,"x":1,"y":1},{"time":2.8333,"x":0,"y":0}]},"W":{"translate":[{"time":0,"x":-92.08,"y":0,"curve":"stepped"},{"time":0.2,"x":-92.08,"y":0},{"time":0.3333,"x":0,"y":0,"curve":"stepped"},{"time":2.6667,"x":0,"y":0},{"time":2.8333,"x":-92.08,"y":0}],"scale":[{"time":0,"x":0,"y":0,"curve":"stepped"},{"time":0.2,"x":0,"y":0},{"time":0.3333,"x":1,"y":1,"curve":"stepped"},{"time":2.6667,"x":1,"y":1},{"time":2.8333,"x":0,"y":0}]},"I":{"translate":[{"time":0,"x":-192.51,"y":0,"curve":"stepped"},{"time":0.2667,"x":-192.51,"y":0,"curve":[0.25,0,0.75,1]},{"time":0.4,"x":0,"y":0,"curve":"stepped"},{"time":2.6667,"x":0,"y":0},{"time":2.8333,"x":-192.51,"y":0}],"scale":[{"time":0,"x":0,"y":0,"curve":"stepped"},{"time":0.2667,"x":0,"y":0,"curve":[0.25,0,0.75,1]},{"time":0.4,"x":1,"y":1,"curve":"stepped"},{"time":2.6667,"x":1,"y":1},{"time":2.8333,"x":0,"y":0}]},"N":{"translate":[{"time":0,"x":-264.63,"y":0,"curve":"stepped"},{"time":0.3333,"x":-264.63,"y":0,"curve":[0.25,0,0.75,1]},{"time":0.4667,"x":0,"y":0,"curve":"stepped"},{"time":2.6667,"x":0,"y":0},{"time":2.8333,"x":-264.63,"y":0}],"scale":[{"time":0,"x":0,"y":0,"curve":"stepped"},{"time":0.3333,"x":0,"y":0,"curve":[0.25,0,0.75,1]},{"time":0.4667,"x":1,"y":1,"curve":"stepped"},{"time":2.6667,"x":1,"y":1},{"time":2.8333,"x":0,"y":0}]},"bone":{"scale":[{"time":0,"x":0,"y":0},{"time":0.3333,"x":5,"y":5}]},"q":{"scale":[{"time":2.6667,"x":1,"y":1},{"time":2.8333,"x":0,"y":0}]},"TONG":{"scale":[{"time":0,"x":0,"y":0,"curve":[0.25,0,0.75,1]},{"time":0.3333,"x":1.4,"y":1.4,"curve":[0.25,0,0.75,1]},{"time":0.4333,"x":1,"y":1}]}}},"megawin":{"slots":{"00_00005":{"color":[{"time":0,"color":"ffffffff"},{"time":0.3333,"color":"ffffff00"}]},"A":{"attachment":[{"time":0,"name":"A"}]},"E":{"attachment":[{"time":0,"name":"E"}]},"G":{"attachment":[{"time":0,"name":"G"}]},"Group 5":{"color":[{"time":0,"color":"ffffff00","curve":"stepped"},{"time":0.1667,"color":"ffffff00"},{"time":0.3333,"color":"ffffffff","curve":"stepped"},{"time":2.6667,"color":"ffffffff"},{"time":2.8333,"color":"ffffff00"}]},"Group 6":{"color":[{"time":0,"color":"ffffff00","curve":"stepped"},{"time":0.1667,"color":"ffffff00"},{"time":0.3333,"color":"ffffffff","curve":"stepped"},{"time":2.6667,"color":"ffffffff"},{"time":2.8333,"color":"ffffff00"}]},"chi/chi_00000":{"color":[{"time":0.8,"color":"ffffffff"},{"time":0.9667,"color":"ffffff0d"}],"attachment":[{"time":0.0333,"name":"chi/chi_00001"},{"time":0.0667,"name":"chi/chi_00002"},{"time":0.1,"name":"chi/chi_00003"},{"time":0.1333,"name":"chi/chi_00004"},{"time":0.1667,"name":"chi/chi_00005"},{"time":0.2,"name":"chi/chi_00006"},{"time":0.2333,"name":"chi/chi_00007"},{"time":0.2667,"name":"chi/chi_00008"},{"time":0.3,"name":"chi/chi_00009"},{"time":0.3333,"name":"chi/chi_00010"},{"time":0.3667,"name":"chi/chi_00011"},{"time":0.4,"name":"chi/chi_00012"},{"time":0.4333,"name":"chi/chi_00013"},{"time":0.4667,"name":"chi/chi_00014"},{"time":0.5,"name":"chi/chi_00015"},{"time":0.5333,"name":"chi/chi_00016"},{"time":0.5667,"name":"chi/chi_00017"},{"time":0.6,"name":"chi/chi_00018"},{"time":0.6333,"name":"chi/chi_00019"},{"time":0.6667,"name":"chi/chi_00020"},{"time":0.7,"name":"chi/chi_00021"},{"time":0.7333,"name":"chi/chi_00022"},{"time":0.7667,"name":"chi/chi_00023"},{"time":0.8,"name":"chi/chi_00024"},{"time":0.8333,"name":"chi/chi_00025"},{"time":0.8667,"name":"chi/chi_00026"},{"time":0.9,"name":"chi/chi_00027"},{"time":0.9333,"name":"chi/chi_00028"},{"time":0.9667,"name":"chi/chi_00029"}]},"chi/chi_0":{"color":[{"time":1.0333,"color":"ffffffff"},{"time":1.4667,"color":"ffffff0d"}],"attachment":[{"time":0,"name":null},{"time":0.5333,"name":"chi/chi_00001"},{"time":0.5667,"name":"chi/chi_00002"},{"time":0.6,"name":"chi/chi_00003"},{"time":0.6333,"name":"chi/chi_00004"},{"time":0.6667,"name":"chi/chi_00005"},{"time":0.7,"name":"chi/chi_00006"},{"time":0.7333,"name":"chi/chi_00007"},{"time":0.7667,"name":"chi/chi_00008"},{"time":0.8,"name":"chi/chi_00009"},{"time":0.8333,"name":"chi/chi_00010"},{"time":0.8667,"name":"chi/chi_00011"},{"time":0.9,"name":"chi/chi_00012"},{"time":0.9333,"name":"chi/chi_00013"},{"time":0.9667,"name":"chi/chi_00014"},{"time":1,"name":"chi/chi_00015"},{"time":1.0333,"name":"chi/chi_00016"},{"time":1.0667,"name":"chi/chi_00017"},{"time":1.1,"name":"chi/chi_00018"},{"time":1.1333,"name":"chi/chi_00019"},{"time":1.1667,"name":"chi/chi_00020"},{"time":1.2,"name":"chi/chi_00021"},{"time":1.2333,"name":"chi/chi_00022"},{"time":1.2667,"name":"chi/chi_00023"},{"time":1.3,"name":"chi/chi_00024"},{"time":1.3333,"name":"chi/chi_00025"},{"time":1.3667,"name":"chi/chi_00026"},{"time":1.4,"name":"chi/chi_00027"},{"time":1.4333,"name":"chi/chi_00028"},{"time":1.4667,"name":"chi/chi_00029"}]},"chi/chi_1":{"color":[{"time":1.5333,"color":"ffffffff"},{"time":1.9667,"color":"ffffff0d"}],"attachment":[{"time":0,"name":null},{"time":1.0333,"name":"chi/chi_00001"},{"time":1.0667,"name":"chi/chi_00002"},{"time":1.1,"name":"chi/chi_00003"},{"time":1.1333,"name":"chi/chi_00004"},{"time":1.1667,"name":"chi/chi_00005"},{"time":1.2,"name":"chi/chi_00006"},{"time":1.2333,"name":"chi/chi_00007"},{"time":1.2667,"name":"chi/chi_00008"},{"time":1.3,"name":"chi/chi_00009"},{"time":1.3333,"name":"chi/chi_00010"},{"time":1.3667,"name":"chi/chi_00011"},{"time":1.4,"name":"chi/chi_00012"},{"time":1.4333,"name":"chi/chi_00013"},{"time":1.4667,"name":"chi/chi_00014"},{"time":1.5,"name":"chi/chi_00015"},{"time":1.5333,"name":"chi/chi_00016"},{"time":1.5667,"name":"chi/chi_00017"},{"time":1.6,"name":"chi/chi_00018"},{"time":1.6333,"name":"chi/chi_00019"},{"time":1.6667,"name":"chi/chi_00020"},{"time":1.7,"name":"chi/chi_00021"},{"time":1.7333,"name":"chi/chi_00022"},{"time":1.7667,"name":"chi/chi_00023"},{"time":1.8,"name":"chi/chi_00024"},{"time":1.8333,"name":"chi/chi_00025"},{"time":1.8667,"name":"chi/chi_00026"},{"time":1.9,"name":"chi/chi_00027"},{"time":1.9333,"name":"chi/chi_00028"},{"time":1.9667,"name":"chi/chi_00029"}]},"chi/chi_2":{"color":[{"time":2.1,"color":"ffffffff"},{"time":2.4667,"color":"ffffff0d"}],"attachment":[{"time":0,"name":null},{"time":1.5333,"name":"chi/chi_00001"},{"time":1.5667,"name":"chi/chi_00002"},{"time":1.6,"name":"chi/chi_00003"},{"time":1.6333,"name":"chi/chi_00004"},{"time":1.6667,"name":"chi/chi_00005"},{"time":1.7,"name":"chi/chi_00006"},{"time":1.7333,"name":"chi/chi_00007"},{"time":1.7667,"name":"chi/chi_00008"},{"time":1.8,"name":"chi/chi_00009"},{"time":1.8333,"name":"chi/chi_00010"},{"time":1.8667,"name":"chi/chi_00011"},{"time":1.9,"name":"chi/chi_00012"},{"time":1.9333,"name":"chi/chi_00013"},{"time":1.9667,"name":"chi/chi_00014"},{"time":2,"name":"chi/chi_00015"},{"time":2.0333,"name":"chi/chi_00016"},{"time":2.0667,"name":"chi/chi_00017"},{"time":2.1,"name":"chi/chi_00018"},{"time":2.1333,"name":"chi/chi_00019"},{"time":2.1667,"name":"chi/chi_00020"},{"time":2.2,"name":"chi/chi_00021"},{"time":2.2333,"name":"chi/chi_00022"},{"time":2.2667,"name":"chi/chi_00023"},{"time":2.3,"name":"chi/chi_00024"},{"time":2.3333,"name":"chi/chi_00025"},{"time":2.3667,"name":"chi/chi_00026"},{"time":2.4,"name":"chi/chi_00027"},{"time":2.4333,"name":"chi/chi_00028"},{"time":2.4667,"name":"chi/chi_00029"}]},"chi/chi_3":{"color":[{"time":2.4667,"color":"ffffffff"},{"time":2.8333,"color":"ffffff0d"}],"attachment":[{"time":0,"name":null},{"time":1.9,"name":"chi/chi_00001"},{"time":1.9333,"name":"chi/chi_00002"},{"time":1.9667,"name":"chi/chi_00003"},{"time":2,"name":"chi/chi_00004"},{"time":2.0333,"name":"chi/chi_00005"},{"time":2.0667,"name":"chi/chi_00006"},{"time":2.1,"name":"chi/chi_00007"},{"time":2.1333,"name":"chi/chi_00008"},{"time":2.1667,"name":"chi/chi_00009"},{"time":2.2,"name":"chi/chi_00010"},{"time":2.2333,"name":"chi/chi_00011"},{"time":2.2667,"name":"chi/chi_00012"},{"time":2.3,"name":"chi/chi_00013"},{"time":2.3333,"name":"chi/chi_00014"},{"time":2.3667,"name":"chi/chi_00015"},{"time":2.4,"name":"chi/chi_00016"},{"time":2.4333,"name":"chi/chi_00017"},{"time":2.4667,"name":"chi/chi_00018"},{"time":2.5,"name":"chi/chi_00019"},{"time":2.5333,"name":"chi/chi_00020"},{"time":2.5667,"name":"chi/chi_00021"},{"time":2.6,"name":"chi/chi_00022"},{"time":2.6333,"name":"chi/chi_00023"},{"time":2.6667,"name":"chi/chi_00024"},{"time":2.7,"name":"chi/chi_00025"},{"time":2.7333,"name":"chi/chi_00026"},{"time":2.7667,"name":"chi/chi_00027"},{"time":2.8,"name":"chi/chi_00028"},{"time":2.8333,"name":"chi/chi_00029"}]},"len/1P_00000":{"color":[{"time":0.1667,"color":"ffffff00"},{"time":0.5,"color":"ffffffff","curve":"stepped"},{"time":0.6667,"color":"ffffffff"},{"time":1,"color":"ffffff00"}],"attachment":[{"time":0,"name":null},{"time":0.1667,"name":"len/1P_00000"},{"time":0.2,"name":"len/1P_00001"},{"time":0.2333,"name":"len/1P_00002"},{"time":0.2667,"name":"len/1P_00003"},{"time":0.3,"name":"len/1P_00004"},{"time":0.3333,"name":"len/1P_00005"},{"time":0.3667,"name":"len/1P_00006"},{"time":0.4,"name":"len/1P_00007"},{"time":0.4333,"name":"len/1P_00008"},{"time":0.4667,"name":"len/1P_00009"},{"time":0.5,"name":"len/1P_00010"},{"time":0.5333,"name":"len/1P_00011"},{"time":0.5667,"name":"len/1P_00012"},{"time":0.6,"name":"len/1P_00013"},{"time":0.6333,"name":"len/1P_00014"},{"time":0.6667,"name":"len/1P_00015"},{"time":0.7,"name":"len/1P_00016"},{"time":0.7333,"name":"len/1P_00017"},{"time":0.7667,"name":"len/1P_00018"},{"time":0.8,"name":"len/1P_00019"},{"time":0.8333,"name":"len/1P_00020"},{"time":0.8667,"name":"len/1P_00021"},{"time":0.9,"name":"len/1P_00022"},{"time":0.9333,"name":"len/1P_00023"},{"time":0.9667,"name":"len/1P_00024"},{"time":1,"name":null}]},"len/1P_0":{"color":[{"time":0.5,"color":"ffffff00"},{"time":0.8333,"color":"ffffffff","curve":"stepped"},{"time":1,"color":"ffffffff"},{"time":1.3333,"color":"ffffff00"}],"attachment":[{"time":0,"name":null},{"time":0.5,"name":"len/1P_00000"},{"time":0.5333,"name":"len/1P_00001"},{"time":0.5667,"name":"len/1P_00002"},{"time":0.6,"name":"len/1P_00003"},{"time":0.6333,"name":"len/1P_00004"},{"time":0.6667,"name":"len/1P_00005"},{"time":0.7,"name":"len/1P_00006"},{"time":0.7333,"name":"len/1P_00007"},{"time":0.7667,"name":"len/1P_00008"},{"time":0.8,"name":"len/1P_00009"},{"time":0.8333,"name":"len/1P_00010"},{"time":0.8667,"name":"len/1P_00011"},{"time":0.9,"name":"len/1P_00012"},{"time":0.9333,"name":"len/1P_00013"},{"time":0.9667,"name":"len/1P_00014"},{"time":1,"name":"len/1P_00015"},{"time":1.0333,"name":"len/1P_00016"},{"time":1.0667,"name":"len/1P_00017"},{"time":1.1,"name":"len/1P_00018"},{"time":1.1333,"name":"len/1P_00019"},{"time":1.1667,"name":"len/1P_00020"},{"time":1.2,"name":"len/1P_00021"},{"time":1.2333,"name":"len/1P_00022"},{"time":1.2667,"name":"len/1P_00023"},{"time":1.3,"name":"len/1P_00024"},{"time":1.3333,"name":null}]},"len/1P_1":{"color":[{"time":0.6667,"color":"ffffff00"},{"time":1.0667,"color":"ffffffff"},{"time":1.5,"color":"ffffff00"}],"attachment":[{"time":0,"name":null},{"time":0.6667,"name":"len/1P_00000"},{"time":0.7,"name":"len/1P_00001"},{"time":0.7333,"name":"len/1P_00002"},{"time":0.7667,"name":"len/1P_00003"},{"time":0.8,"name":"len/1P_00004"},{"time":0.8333,"name":"len/1P_00005"},{"time":0.8667,"name":"len/1P_00006"},{"time":0.9,"name":"len/1P_00007"},{"time":0.9333,"name":"len/1P_00008"},{"time":0.9667,"name":"len/1P_00009"},{"time":1,"name":"len/1P_00010"},{"time":1.0333,"name":"len/1P_00011"},{"time":1.0667,"name":"len/1P_00012"},{"time":1.1,"name":"len/1P_00013"},{"time":1.1333,"name":"len/1P_00014"},{"time":1.1667,"name":"len/1P_00015"},{"time":1.2,"name":"len/1P_00016"},{"time":1.2333,"name":"len/1P_00017"},{"time":1.2667,"name":"len/1P_00018"},{"time":1.3,"name":"len/1P_00019"},{"time":1.3333,"name":"len/1P_00020"},{"time":1.3667,"name":"len/1P_00021"},{"time":1.4,"name":"len/1P_00022"},{"time":1.4333,"name":"len/1P_00023"},{"time":1.4667,"name":"len/1P_00024"},{"time":1.5,"name":null}]},"len/1P_2":{"color":[{"time":0.8333,"color":"ffffff00"},{"time":1.2333,"color":"ffffffff"},{"time":1.6667,"color":"ffffff00"}],"attachment":[{"time":0,"name":null},{"time":0.8333,"name":"len/1P_00000"},{"time":0.8667,"name":"len/1P_00001"},{"time":0.9,"name":"len/1P_00002"},{"time":0.9333,"name":"len/1P_00003"},{"time":0.9667,"name":"len/1P_00004"},{"time":1,"name":"len/1P_00005"},{"time":1.0333,"name":"len/1P_00006"},{"time":1.0667,"name":"len/1P_00007"},{"time":1.1,"name":"len/1P_00008"},{"time":1.1333,"name":"len/1P_00009"},{"time":1.1667,"name":"len/1P_00010"},{"time":1.2,"name":"len/1P_00011"},{"time":1.2333,"name":"len/1P_00012"},{"time":1.2667,"name":"len/1P_00013"},{"time":1.3,"name":"len/1P_00014"},{"time":1.3333,"name":"len/1P_00015"},{"time":1.3667,"name":"len/1P_00016"},{"time":1.4,"name":"len/1P_00017"},{"time":1.4333,"name":"len/1P_00018"},{"time":1.4667,"name":"len/1P_00019"},{"time":1.5,"name":"len/1P_00020"},{"time":1.5333,"name":"len/1P_00021"},{"time":1.5667,"name":"len/1P_00022"},{"time":1.6,"name":"len/1P_00023"},{"time":1.6333,"name":"len/1P_00024"},{"time":1.6667,"name":null}]},"len/1P_3":{"color":[{"time":1,"color":"ffffff00"},{"time":1.4,"color":"ffffffff"},{"time":1.8333,"color":"ffffff00"}],"attachment":[{"time":0,"name":null},{"time":1,"name":"len/1P_00000"},{"time":1.0333,"name":"len/1P_00001"},{"time":1.0667,"name":"len/1P_00002"},{"time":1.1,"name":"len/1P_00003"},{"time":1.1333,"name":"len/1P_00004"},{"time":1.1667,"name":"len/1P_00005"},{"time":1.2,"name":"len/1P_00006"},{"time":1.2333,"name":"len/1P_00007"},{"time":1.2667,"name":"len/1P_00008"},{"time":1.3,"name":"len/1P_00009"},{"time":1.3333,"name":"len/1P_00010"},{"time":1.3667,"name":"len/1P_00011"},{"time":1.4,"name":"len/1P_00012"},{"time":1.4333,"name":"len/1P_00013"},{"time":1.4667,"name":"len/1P_00014"},{"time":1.5,"name":"len/1P_00015"},{"time":1.5333,"name":"len/1P_00016"},{"time":1.5667,"name":"len/1P_00017"},{"time":1.6,"name":"len/1P_00018"},{"time":1.6333,"name":"len/1P_00019"},{"time":1.6667,"name":"len/1P_00020"},{"time":1.7,"name":"len/1P_00021"},{"time":1.7333,"name":"len/1P_00022"},{"time":1.7667,"name":"len/1P_00023"},{"time":1.8,"name":"len/1P_00024"},{"time":1.8333,"name":null}]},"len/1P_4":{"color":[{"time":1.1667,"color":"ffffff00"},{"time":1.5667,"color":"ffffffff"},{"time":2,"color":"ffffff00"}],"attachment":[{"time":0,"name":null},{"time":1.1667,"name":"len/1P_00000"},{"time":1.2,"name":"len/1P_00001"},{"time":1.2333,"name":"len/1P_00002"},{"time":1.2667,"name":"len/1P_00003"},{"time":1.3,"name":"len/1P_00004"},{"time":1.3333,"name":"len/1P_00005"},{"time":1.3667,"name":"len/1P_00006"},{"time":1.4,"name":"len/1P_00007"},{"time":1.4333,"name":"len/1P_00008"},{"time":1.4667,"name":"len/1P_00009"},{"time":1.5,"name":"len/1P_00010"},{"time":1.5333,"name":"len/1P_00011"},{"time":1.5667,"name":"len/1P_00012"},{"time":1.6,"name":"len/1P_00013"},{"time":1.6333,"name":"len/1P_00014"},{"time":1.6667,"name":"len/1P_00015"},{"time":1.7,"name":"len/1P_00016"},{"time":1.7333,"name":"len/1P_00017"},{"time":1.7667,"name":"len/1P_00018"},{"time":1.8,"name":"len/1P_00019"},{"time":1.8333,"name":"len/1P_00020"},{"time":1.8667,"name":"len/1P_00021"},{"time":1.9,"name":"len/1P_00022"},{"time":1.9333,"name":"len/1P_00023"},{"time":1.9667,"name":"len/1P_00024"},{"time":2,"name":null}]},"len/1P_5":{"color":[{"time":1.3333,"color":"ffffff00"},{"time":1.7333,"color":"ffffffff"},{"time":2.1667,"color":"ffffff00"}],"attachment":[{"time":0,"name":null},{"time":1.3333,"name":"len/1P_00000"},{"time":1.3667,"name":"len/1P_00001"},{"time":1.4,"name":"len/1P_00002"},{"time":1.4333,"name":"len/1P_00003"},{"time":1.4667,"name":"len/1P_00004"},{"time":1.5,"name":"len/1P_00005"},{"time":1.5333,"name":"len/1P_00006"},{"time":1.5667,"name":"len/1P_00007"},{"time":1.6,"name":"len/1P_00008"},{"time":1.6333,"name":"len/1P_00009"},{"time":1.6667,"name":"len/1P_00010"},{"time":1.7,"name":"len/1P_00011"},{"time":1.7333,"name":"len/1P_00012"},{"time":1.7667,"name":"len/1P_00013"},{"time":1.8,"name":"len/1P_00014"},{"time":1.8333,"name":"len/1P_00015"},{"time":1.8667,"name":"len/1P_00016"},{"time":1.9,"name":"len/1P_00017"},{"time":1.9333,"name":"len/1P_00018"},{"time":1.9667,"name":"len/1P_00019"},{"time":2,"name":"len/1P_00020"},{"time":2.0333,"name":"len/1P_00021"},{"time":2.0667,"name":"len/1P_00022"},{"time":2.1,"name":"len/1P_00023"},{"time":2.1333,"name":"len/1P_00024"},{"time":2.1667,"name":null}]},"len/1P_6":{"color":[{"time":1.5,"color":"ffffff00"},{"time":1.9,"color":"ffffffff"},{"time":2.3333,"color":"ffffff00"}],"attachment":[{"time":0,"name":null},{"time":1.5,"name":"len/1P_00000"},{"time":1.5333,"name":"len/1P_00001"},{"time":1.5667,"name":"len/1P_00002"},{"time":1.6,"name":"len/1P_00003"},{"time":1.6333,"name":"len/1P_00004"},{"time":1.6667,"name":"len/1P_00005"},{"time":1.7,"name":"len/1P_00006"},{"time":1.7333,"name":"len/1P_00007"},{"time":1.7667,"name":"len/1P_00008"},{"time":1.8,"name":"len/1P_00009"},{"time":1.8333,"name":"len/1P_00010"},{"time":1.8667,"name":"len/1P_00011"},{"time":1.9,"name":"len/1P_00012"},{"time":1.9333,"name":"len/1P_00013"},{"time":1.9667,"name":"len/1P_00014"},{"time":2,"name":"len/1P_00015"},{"time":2.0333,"name":"len/1P_00016"},{"time":2.0667,"name":"len/1P_00017"},{"time":2.1,"name":"len/1P_00018"},{"time":2.1333,"name":"len/1P_00019"},{"time":2.1667,"name":"len/1P_00020"},{"time":2.2,"name":"len/1P_00021"},{"time":2.2333,"name":"len/1P_00022"},{"time":2.2667,"name":"len/1P_00023"},{"time":2.3,"name":"len/1P_00024"},{"time":2.3333,"name":null}]},"len/1P_7":{"color":[{"time":1.6667,"color":"ffffff00"},{"time":2.0667,"color":"ffffffff"},{"time":2.5,"color":"ffffff00"}],"attachment":[{"time":0,"name":null},{"time":1.6667,"name":"len/1P_00000"},{"time":1.7,"name":"len/1P_00001"},{"time":1.7333,"name":"len/1P_00002"},{"time":1.7667,"name":"len/1P_00003"},{"time":1.8,"name":"len/1P_00004"},{"time":1.8333,"name":"len/1P_00005"},{"time":1.8667,"name":"len/1P_00006"},{"time":1.9,"name":"len/1P_00007"},{"time":1.9333,"name":"len/1P_00008"},{"time":1.9667,"name":"len/1P_00009"},{"time":2,"name":"len/1P_00010"},{"time":2.0333,"name":"len/1P_00011"},{"time":2.0667,"name":"len/1P_00012"},{"time":2.1,"name":"len/1P_00013"},{"time":2.1333,"name":"len/1P_00014"},{"time":2.1667,"name":"len/1P_00015"},{"time":2.2,"name":"len/1P_00016"},{"time":2.2333,"name":"len/1P_00017"},{"time":2.2667,"name":"len/1P_00018"},{"time":2.3,"name":"len/1P_00019"},{"time":2.3333,"name":"len/1P_00020"},{"time":2.3667,"name":"len/1P_00021"},{"time":2.4,"name":"len/1P_00022"},{"time":2.4333,"name":"len/1P_00023"},{"time":2.4667,"name":"len/1P_00024"},{"time":2.5,"name":null}]},"len/1P_8":{"color":[{"time":1.8333,"color":"ffffff00"},{"time":2.2333,"color":"ffffffff"},{"time":2.6667,"color":"ffffff00"}],"attachment":[{"time":0,"name":null},{"time":1.8333,"name":"len/1P_00000"},{"time":1.8667,"name":"len/1P_00001"},{"time":1.9,"name":"len/1P_00002"},{"time":1.9333,"name":"len/1P_00003"},{"time":1.9667,"name":"len/1P_00004"},{"time":2,"name":"len/1P_00005"},{"time":2.0333,"name":"len/1P_00006"},{"time":2.0667,"name":"len/1P_00007"},{"time":2.1,"name":"len/1P_00008"},{"time":2.1333,"name":"len/1P_00009"},{"time":2.1667,"name":"len/1P_00010"},{"time":2.2,"name":"len/1P_00011"},{"time":2.2333,"name":"len/1P_00012"},{"time":2.2667,"name":"len/1P_00013"},{"time":2.3,"name":"len/1P_00014"},{"time":2.3333,"name":"len/1P_00015"},{"time":2.3667,"name":"len/1P_00016"},{"time":2.4,"name":"len/1P_00017"},{"time":2.4333,"name":"len/1P_00018"},{"time":2.4667,"name":"len/1P_00019"},{"time":2.5,"name":"len/1P_00020"},{"time":2.5333,"name":"len/1P_00021"},{"time":2.5667,"name":"len/1P_00022"},{"time":2.6,"name":"len/1P_00023"},{"time":2.6333,"name":"len/1P_00024"},{"time":2.6667,"name":null}]},"len/1P_9":{"color":[{"time":2,"color":"ffffff00"},{"time":2.4,"color":"ffffffff"},{"time":2.8333,"color":"ffffff00"}],"attachment":[{"time":0,"name":null},{"time":2,"name":"len/1P_00000"},{"time":2.0333,"name":"len/1P_00001"},{"time":2.0667,"name":"len/1P_00002"},{"time":2.1,"name":"len/1P_00003"},{"time":2.1333,"name":"len/1P_00004"},{"time":2.1667,"name":"len/1P_00005"},{"time":2.2,"name":"len/1P_00006"},{"time":2.2333,"name":"len/1P_00007"},{"time":2.2667,"name":"len/1P_00008"},{"time":2.3,"name":"len/1P_00009"},{"time":2.3333,"name":"len/1P_00010"},{"time":2.3667,"name":"len/1P_00011"},{"time":2.4,"name":"len/1P_00012"},{"time":2.4333,"name":"len/1P_00013"},{"time":2.4667,"name":"len/1P_00014"},{"time":2.5,"name":"len/1P_00015"},{"time":2.5333,"name":"len/1P_00016"},{"time":2.5667,"name":"len/1P_00017"},{"time":2.6,"name":"len/1P_00018"},{"time":2.6333,"name":"len/1P_00019"},{"time":2.6667,"name":"len/1P_00020"},{"time":2.7,"name":"len/1P_00021"},{"time":2.7333,"name":"len/1P_00022"},{"time":2.7667,"name":"len/1P_00023"},{"time":2.8,"name":"len/1P_00024"},{"time":2.8333,"name":null}]}},"bones":{"E":{"translate":[{"time":0,"x":248.25,"y":0,"curve":[0.25,0,0.75,1]},{"time":0.1333,"x":-29.97,"y":0,"curve":"stepped"},{"time":2.6667,"x":-29.97,"y":0},{"time":2.8333,"x":248.25,"y":0}],"scale":[{"time":0,"x":0,"y":0,"curve":[0.25,0,0.75,1]},{"time":0.1333,"x":1,"y":1,"curve":"stepped"},{"time":2.6667,"x":1,"y":1},{"time":2.8333,"x":0,"y":0}]},"G":{"translate":[{"time":0,"x":170.72,"y":0,"curve":"stepped"},{"time":0.0667,"x":170.72,"y":0,"curve":[0.25,0,0.75,1]},{"time":0.2,"x":-1.94,"y":0,"curve":"stepped"},{"time":2.6667,"x":-1.94,"y":0},{"time":2.8333,"x":170.72,"y":0}],"scale":[{"time":0,"x":0,"y":0,"curve":"stepped"},{"time":0.0667,"x":0,"y":0,"curve":[0.25,0,0.75,1]},{"time":0.2,"x":1,"y":1,"curve":"stepped"},{"time":2.6667,"x":1,"y":1},{"time":2.8333,"x":0,"y":0}]},"A":{"translate":[{"time":0,"x":80.84,"y":0,"curve":"stepped"},{"time":0.1333,"x":80.84,"y":0,"curve":[0.25,0,0.75,1]},{"time":0.2667,"x":21.12,"y":0,"curve":"stepped"},{"time":2.6667,"x":21.12,"y":0},{"time":2.8333,"x":80.84,"y":0}],"scale":[{"time":0,"x":0,"y":0,"curve":"stepped"},{"time":0.1333,"x":0,"y":0,"curve":[0.25,0,0.75,1]},{"time":0.2667,"x":1,"y":1,"curve":"stepped"},{"time":2.6667,"x":1,"y":1},{"time":2.8333,"x":0,"y":0}]},"W":{"translate":[{"time":0,"x":-92.08,"y":0,"curve":"stepped"},{"time":0.2,"x":-92.08,"y":0},{"time":0.3333,"x":0,"y":0,"curve":"stepped"},{"time":2.6667,"x":0,"y":0},{"time":2.8333,"x":-92.08,"y":0}],"scale":[{"time":0,"x":0,"y":0,"curve":"stepped"},{"time":0.2,"x":0,"y":0},{"time":0.3333,"x":1,"y":1,"curve":"stepped"},{"time":2.6667,"x":1,"y":1},{"time":2.8333,"x":0,"y":0}]},"I":{"translate":[{"time":0,"x":-192.51,"y":0,"curve":"stepped"},{"time":0.2667,"x":-192.51,"y":0,"curve":[0.25,0,0.75,1]},{"time":0.4,"x":0,"y":0,"curve":"stepped"},{"time":2.6667,"x":0,"y":0},{"time":2.8333,"x":-192.51,"y":0}],"scale":[{"time":0,"x":0,"y":0,"curve":"stepped"},{"time":0.2667,"x":0,"y":0,"curve":[0.25,0,0.75,1]},{"time":0.4,"x":1,"y":1,"curve":"stepped"},{"time":2.6667,"x":1,"y":1},{"time":2.8333,"x":0,"y":0}]},"N":{"translate":[{"time":0,"x":-264.63,"y":0,"curve":"stepped"},{"time":0.3333,"x":-264.63,"y":0,"curve":[0.25,0,0.75,1]},{"time":0.4667,"x":0,"y":0,"curve":"stepped"},{"time":2.6667,"x":0,"y":0},{"time":2.8333,"x":-264.63,"y":0}],"scale":[{"time":0,"x":0,"y":0,"curve":"stepped"},{"time":0.3333,"x":0,"y":0,"curve":[0.25,0,0.75,1]},{"time":0.4667,"x":1,"y":1,"curve":"stepped"},{"time":2.6667,"x":1,"y":1},{"time":2.8333,"x":0,"y":0}]},"bone":{"scale":[{"time":0,"x":0,"y":0},{"time":0.3333,"x":5,"y":5}]},"q":{"scale":[{"time":2.6667,"x":1,"y":1},{"time":2.8333,"x":0,"y":0}]},"TONG":{"scale":[{"time":0,"x":0,"y":0,"curve":[0.25,0,0.75,1]},{"time":0.3333,"x":1.4,"y":1.4,"curve":[0.25,0,0.75,1]},{"time":0.4333,"x":1,"y":1}]},"TEXTTT":{"translate":[{"time":0,"x":76.83,"y":0}]},"M":{"translate":[{"time":2.6667,"x":0,"y":0},{"time":2.8333,"x":315.66,"y":0}],"scale":[{"time":2.6667,"x":1,"y":1},{"time":2.8333,"x":0,"y":0}]}}}}}