{"skeleton":{"hash":"PfhahCmgXvKfMEy2e++DGNpeFsI","spine":"3.6.53","width":117.33,"height":90,"images":""},"bones":[{"name":"root"},{"name":"bone","parent":"root","length":138.03,"rotation":88.75,"x":-10.5,"y":-59.65},{"name":"light","parent":"root","x":-16.33,"scaleX":0.5}],"slots":[{"name":"small1","bone":"bone","attachment":"small2"},{"name":"light","bone":"light","attachment":"light"}],"skins":{"default":{"light":{"light":{"width":200,"height":90}},"small1":{"small1":{"x":59.86,"y":-9.2,"rotation":-88.75,"width":93,"height":96},"small2":{"x":59.86,"y":-9.2,"rotation":-88.75,"width":102,"height":90},"small3":{"x":59.86,"y":-9.2,"rotation":-88.75,"width":92,"height":98},"small4":{"x":59.86,"y":-9.2,"rotation":-88.75,"width":81,"height":91}}}},"animations":{"bich":{"slots":{"light":{"color":[{"time":0,"color":"ffffff00","curve":"stepped"},{"time":0.1667,"color":"ffffff00"},{"time":0.2333,"color":"ffffffff","curve":"stepped"},{"time":0.4,"color":"ffffffff"},{"time":0.5,"color":"ffffff00","curve":"stepped"},{"time":0.6,"color":"ffffff00"},{"time":0.6667,"color":"ffffffff","curve":"stepped"},{"time":0.7667,"color":"ffffffff"},{"time":0.8333,"color":"ffffff00"}]},"small1":{"attachment":[{"time":0,"name":"small1"}]}},"bones":{"bone":{"translate":[{"time":0,"x":0,"y":0,"curve":"stepped"},{"time":0.1667,"x":0,"y":0,"curve":[0.25,0,0.75,1]},{"time":0.5,"x":0,"y":9.72,"curve":[0.25,0,0.75,1]},{"time":0.8333,"x":0,"y":0}],"scale":[{"time":0,"x":0.963,"y":1.037,"curve":[0.381,0.55,0.742,1]},{"time":0.0667,"x":1,"y":1,"curve":[0.25,0,0.75,1]},{"time":0.2333,"x":0.9,"y":1.1,"curve":[0.25,0,0.75,1]},{"time":0.5667,"x":1.1,"y":0.9,"curve":[0.25,0,0.75,1]},{"time":0.9,"x":0.9,"y":1.1,"curve":[0.245,0,0.637,0.56]},{"time":1,"x":0.963,"y":1.037}]},"light":{"translate":[{"time":0,"x":14.74,"y":-41.96,"curve":"stepped"},{"time":0.1667,"x":14.74,"y":-41.96,"curve":[0.305,0,0.64,0.36]},{"time":0.5,"x":14.74,"y":63.31,"curve":"stepped"},{"time":0.6,"x":14.74,"y":63.31,"curve":[0.25,0,0.75,1]},{"time":0.8333,"x":14.74,"y":-41.96}]}}},"co":{"slots":{"light":{"color":[{"time":0,"color":"ffffff00","curve":"stepped"},{"time":0.1667,"color":"ffffff00"},{"time":0.2333,"color":"ffffffff","curve":"stepped"},{"time":0.4,"color":"ffffffff"},{"time":0.5,"color":"ffffff00","curve":"stepped"},{"time":0.6,"color":"ffffff00"},{"time":0.6667,"color":"ffffffff","curve":"stepped"},{"time":0.7667,"color":"ffffffff"},{"time":0.8333,"color":"ffffff00"}]},"small1":{"attachment":[{"time":0,"name":"small2"}]}},"bones":{"bone":{"translate":[{"time":0,"x":0,"y":0,"curve":"stepped"},{"time":0.1667,"x":0,"y":0,"curve":[0.25,0,0.75,1]},{"time":0.5,"x":0,"y":9.72,"curve":[0.25,0,0.75,1]},{"time":0.8333,"x":0,"y":0}],"scale":[{"time":0,"x":0.963,"y":1.037,"curve":[0.381,0.55,0.742,1]},{"time":0.0667,"x":1,"y":1,"curve":[0.25,0,0.75,1]},{"time":0.2333,"x":0.9,"y":1.1,"curve":[0.25,0,0.75,1]},{"time":0.5667,"x":1.1,"y":0.9,"curve":[0.25,0,0.75,1]},{"time":0.9,"x":0.9,"y":1.1,"curve":[0.245,0,0.637,0.56]},{"time":1,"x":0.963,"y":1.037}]},"light":{"translate":[{"time":0,"x":16.33,"y":-42.37,"curve":"stepped"},{"time":0.1667,"x":16.33,"y":-42.37,"curve":[0.25,0,0.75,1]},{"time":0.5,"x":16.33,"y":58.5,"curve":"stepped"},{"time":0.6,"x":16.33,"y":58.5,"curve":[0.25,0,0.75,1]},{"time":0.8333,"x":16.33,"y":-42.37}]}}},"tep":{"slots":{"light":{"color":[{"time":0,"color":"ffffff00","curve":"stepped"},{"time":0.1667,"color":"ffffff00"},{"time":0.2333,"color":"ffffffff","curve":"stepped"},{"time":0.4,"color":"ffffffff"},{"time":0.5,"color":"ffffff00","curve":"stepped"},{"time":0.6,"color":"ffffff00"},{"time":0.6667,"color":"ffffffff","curve":"stepped"},{"time":0.7667,"color":"ffffffff"},{"time":0.8333,"color":"ffffff00"}]},"small1":{"attachment":[{"time":0,"name":"small3"}]}},"bones":{"bone":{"translate":[{"time":0,"x":0,"y":0,"curve":"stepped"},{"time":0.1667,"x":0,"y":0,"curve":[0.25,0,0.75,1]},{"time":0.5,"x":0,"y":9.72,"curve":[0.25,0,0.75,1]},{"time":0.8333,"x":0,"y":0}],"scale":[{"time":0,"x":0.963,"y":1.037,"curve":[0.381,0.55,0.742,1]},{"time":0.0667,"x":1,"y":1,"curve":[0.25,0,0.75,1]},{"time":0.2333,"x":0.9,"y":1.1,"curve":[0.25,0,0.75,1]},{"time":0.5667,"x":1.1,"y":0.9,"curve":[0.25,0,0.75,1]},{"time":0.9,"x":0.9,"y":1.1,"curve":[0.245,0,0.637,0.56]},{"time":1,"x":0.963,"y":1.037}]},"light":{"translate":[{"time":0,"x":16.33,"y":-30.53,"curve":"stepped"},{"time":0.1667,"x":16.33,"y":-30.53,"curve":[0.25,0,0.75,1]},{"time":0.5,"x":16.33,"y":61.24,"curve":"stepped"},{"time":0.6,"x":16.33,"y":61.24,"curve":[0.25,0,0.75,1]},{"time":0.8333,"x":16.33,"y":-30.53}]}}},"zo":{"slots":{"light":{"color":[{"time":0,"color":"ffffff00","curve":"stepped"},{"time":0.1667,"color":"ffffff00"},{"time":0.2333,"color":"ffffffff","curve":"stepped"},{"time":0.4,"color":"ffffffff"},{"time":0.5,"color":"ffffff00","curve":"stepped"},{"time":0.6,"color":"ffffff00"},{"time":0.6667,"color":"ffffffff","curve":"stepped"},{"time":0.7667,"color":"ffffffff"},{"time":0.8333,"color":"ffffff00"}]},"small1":{"attachment":[{"time":0,"name":"small4"}]}},"bones":{"bone":{"translate":[{"time":0,"x":0,"y":0,"curve":"stepped"},{"time":0.1667,"x":0,"y":0,"curve":[0.25,0,0.75,1]},{"time":0.5,"x":0,"y":9.72,"curve":[0.25,0,0.75,1]},{"time":0.8333,"x":0,"y":0}],"scale":[{"time":0,"x":0.963,"y":1.037,"curve":[0.381,0.55,0.742,1]},{"time":0.0667,"x":1,"y":1,"curve":[0.25,0,0.75,1]},{"time":0.2333,"x":0.9,"y":1.1,"curve":[0.25,0,0.75,1]},{"time":0.5667,"x":1.1,"y":0.9,"curve":[0.25,0,0.75,1]},{"time":0.9,"x":0.9,"y":1.1,"curve":[0.245,0,0.637,0.56]},{"time":1,"x":0.963,"y":1.037}]},"light":{"translate":[{"time":0,"x":16.33,"y":-38.84,"curve":"stepped"},{"time":0.1667,"x":16.33,"y":-38.84,"curve":[0.25,0,0.75,1]},{"time":0.5,"x":16.33,"y":57.08,"curve":"stepped"},{"time":0.6,"x":16.33,"y":57.08,"curve":[0.25,0,0.75,1]},{"time":0.8333,"x":16.33,"y":-38.84}]}}}}}