{"skeleton":{"hash":"Bp49ix7bqZ4Sb/kzwX8bCIAq0P0","spine":"3.6.46","width":229.49,"height":69,"images":""},"bones":[{"name":"button_declare"},{"name":"bone","parent":"button_declare","length":36.11,"rotation":89.55,"x":-45.33,"y":2.8,"scaleX":0.85,"scaleY":0.85},{"name":"bone2","parent":"button_declare","length":33.21,"rotation":88.65,"x":56.76,"y":4.05,"scaleX":0.85,"scaleY":0.85}],"slots":[{"name":"light","bone":"bone","attachment":"light"},{"name":"light - Copy","bone":"bone2","attachment":"light - Copy"}],"skins":{"default":{"light":{"light":{"x":0.44,"y":36.17,"rotation":-89.55,"width":82,"height":80}},"light - Copy":{"light - Copy":{"x":1.18,"y":-31.69,"rotation":-88.65,"width":82,"height":80}}}},"animations":{"animation":{"slots":{"light":{"color":[{"time":0,"color":"ffffff00","curve":[0.25,0,0.75,1]},{"time":0.3333,"color":"ffffffff","curve":"stepped"},{"time":1,"color":"ffffffff"},{"time":1.3333,"color":"ffffff00"}]},"light - Copy":{"color":[{"time":0,"color":"ffffff00","curve":[0.25,0,0.75,1]},{"time":0.3333,"color":"ffffffff","curve":"stepped"},{"time":1,"color":"ffffffff"},{"time":1.3333,"color":"ffffff00","curve":"stepped"},{"time":2.3333,"color":"ffffff00"}]}},"bones":{"bone":{"translate":[{"time":0,"x":0,"y":0,"curve":[0.25,0,0.75,1]},{"time":1.3333,"x":146.49,"y":0}]},"bone2":{"translate":[{"time":0,"x":0,"y":0,"curve":[0.25,0,0.75,1]},{"time":1.3333,"x":-157.29,"y":0}]}}}}}